Workbook

Sheet 1. Overview & Checklist
A1: ZORA CLIENT ONBOARDING TEMPLATE — OVERVIEW & CHECKLIST
A2: Use this checklist to track progress across all onboarding sheets. Complete sheets in order — later sheets depend on earlier ones. Sheet 1 (this sheet) is completed last as a summary of everything gathered.
A3: ℹ HOW TO USE THIS TEMPLATE: 1) Start with Sheet 2 (Table Info) — fill in the client's database tables. 2) Proceed through sheets in order. 3) Yellow rows = pre-filled examples from the reference model — replace with client data. 4) Update the Status column below as each sheet is completed. 5) The AI team uses all sheets to configure and test the product before go-live.
A4: PROJECT INFORMATION
B5: Client Name | C5: Covestro
B6: Project / Engagement Name | C6: Zora AI Pilot
B7: Product Module(s) in Scope | C7: [e.g. Ask Zora, KPI Cards, Performance Pulse, Daily News]
B8: Primary Client Contact | C8: [Name, Title, Email]
B9: Zora Team Lead | C9: [Name]
B10: Target Go-Live Date | C10: [DD/MM/YYYY]
B11: Data Source System(s) | C11: [e.g. SAP S/4HANA, Oracle EBS, Salesforce CRM, Excel Budget Model]
B12: Reporting Currency | C12: [e.g. USD — all monetary amounts in reporting currency]
B13: Fiscal Year Start Month | C13: [e.g. January — or April if non-calendar fiscal year]
A15: SHEET-BY-SHEET COMPLETION CHECKLIST
A16: # | B16: Sheet Name | C16: What This Sheet Captures | D16: Data Provider (Client / Team) | E16: Format Required | F16: Priority | G16: Status
A17: 2 | B17: Table Info | C17: All database tables the AI can query: table names, grain (what one row represents), when to use each table, when NOT to use it, and which metrics each table supports. | D17: Client (data/IT team) + Zora Team validation | E17: Fill the Table Info sheet directly. One row per table. | F17: 🔴 Critical (required first) | G17: NOT STARTED
A18: 3 | B18: Column Info | C18: Every column in every table: business-friendly name, plain-English description, data type, sample values, and friendly_names (the phrases users say that map to this column). | D18: Client (data/IT team) + Zora Team validation | E18: Fill the Column Info sheet. One row per column. friendly_names column is especially important — more = better. | F18: 🔴 Critical (required first) | G18: NOT STARTED
A19: 4 | B19: Metrics | C19: Every metric the AI can compute: formula, keywords that trigger it, SQL template with {placeholders}, critical usage notes, and example arguments. | D19: Zora Team (with client sign-off on formulas) | E19: Fill the Metrics sheet. One row per metric. Client must confirm formula definitions (e.g. how they define DSO, what budget version to use). | F19: 🔴 Critical | G19: NOT STARTED
A20: 5 | B20: GT — Ask Zora | C20: Ground truth question-answer pairs: sample user questions, source tables, step-by-step calculation logic, verified SQL, and expected numerical answers. | D20: Functional team (client SMEs) + Zora Team builds SQL | E20: Fill the GT sheet. Minimum 10 rows covering all key question types. Client SMEs must verify expected_answer values against their source of truth. | F20: 🔴 Critical | G20: NOT STARTED
A21: 6 | B21: KPI Cards | C21: KPI card widget definitions: the headline SQL (returns one number), the comparison badge SQL (e.g. MoM change), footnote, target value, and favorable direction. | D21: Functional team (client) + Zora Team builds SQL | E21: Fill the KPI Cards sheet. One row per card. Each SQL must return exactly ONE row. Test against live data before marking complete. | F21: 🟡 High | G21: NOT STARTED
A22: 7 | B22: Performance Pulse | C22: Performance Pulse widget definitions: the SQL that retrieves data, ground truth numbers, the exact output format template (chart + table + narrative structure), and a sample prompt that triggers each widget. | D22: Functional team (client) + Zora Team | E22: Fill the Performance Pulse sheet. One row per widget. ground_truth must be verified. output_format is the exact AI response template. | F22: 🟡 High | G22: NOT STARTED
A23: 8 | B23: Daily News Logic | C23: Daily auto-generated news items: what each item shows, headline and body templates, calculation logic, verified SQL, ground truth numbers, and chart specification. | D23: Functional team (client) + Zora Team | E23: Fill the Daily News sheet. One row per news item. Test SQL against live data. Mark status PASS only when AI output matches ground truth. | F23: 🟡 High | G23: NOT STARTED
A24: 9 | B24: Fiscal & Rounding Rules | C24: Client-specific configuration: fiscal year start month, fiscal quarter mapping, reporting currency, number formatting rules, rounding conventions, budget version to use, and KPI targets. | D24: Client (Finance / FP&A team) | E24: Fill the Fiscal & Rounding Rules sheet directly. All fields required — incorrect fiscal config causes wrong period filters in every query. | F24: 🔴 Critical | G24: NOT STARTED
A25: 10 | B25: Requirements & Notes | C25: Master prompt context (who the AI is and how it should behave), known data issues and limitations, open questions for the client, and sign/rounding conventions. | D25: Zora Team + Client review | E25: Fill the Requirements & Notes sheet. Master Prompt Context section is particularly important — it defines AI behaviour. | F25: 🟡 High | G25: NOT STARTED
A27: STATUS KEY: NOT STARTED = work not begun | IN PROGRESS = actively being filled | CLIENT REVIEW = submitted to client for verification | COMPLETE = verified and signed off
A29: ⚠ DEPENDENCY ORDER: Sheets 2 (Table Info) and 3 (Column Info) must be completed FIRST — all SQL in later sheets references the exact table and column names defined there. Sheet 4 (Metrics) must be complete before Sheet 5 (GT). Sheet 9 (Fiscal & Rounding Rules) must be complete before any AI testing begins.

Sheet 2. Table Info
A1: TABLE INFO
A2: One row per table in the client database. Describes purpose, grain, usage rules and key joins. Fill every column — the AI uses this to decide WHICH table to query.
A3: ℹ Instructions: Add one row per table. table_name must exactly match the database table name. grain = what one row represents (e.g. 'one row per billing line'). when_to_use / when_not_to_use are critical — they prevent the AI from joining wrong tables. Yellow rows are filled examples; replace with your own data.
A4: Covestro | J4: Covestro - meta data
A5: table_name | B5: alias | C5: table_type | D5: primary_key | E5: grain | F5: when_to_use | G5: when_not_to_use | H5: string_columns | I5: possible_metrics | J5: notes
A6: AR_KeyDate | B6: kd | F6: Use for accounts receivable snapshot analysis at a specific reporting date. Use for overdue receivables, not-yet-due receivables, receivables balances, WAT Target, WOC Target, receivables aging, credit exposure, customer payment terms, and working capital reporting. Slice by customer, geography, product, sales organization, industry, marketing hierarchy, or reporting unit. | G6: Do not use for sales revenue, sales volume, margin, product cost, shipment, or OTIF analyses. Do not use for operational collection performance trends over time; use AR-PM instead | H6: ['BG, booked', 'BG, booked2', 'Company Code', 'Company Code2', 'Core Business Indicator', 'Core Business Indicator2', 'Country ship-to', 'Country ship-to2', 'Country sold-to', 'Country sold-to2', 'Cust Hier1', 'Cust Hier12', 'Cust Hier2', 'Cust Hier22', 'Cust Hier3', 'Cust Hier32', 'Customer Channel', 'Customer Channel2', 'Customer Cluster', 'Customer Cluster2', 'Extern. Sales Office', 'Extern. Sales Office2', 'FI-ML0', 'FI-ML02', 'Fiscal year/period', 'Fiscal year/period2', 'Int. Sales Group', 'Int. Sales Group2', 'Key Industry', 'Key Industry2', 'Marketing Customer ship-to', 'Marketing Customer ship-to2', 'Marketing Customer sold-to', 'Marketing Customer sold-to2', 'Marketing Level 0', 'Marketing Level 02', 'Marketing Level 1', 'Marketing Level 12', 'Marketing Level 2', 'Marketing Level 22', 'Marketing Level 3', 'Marketing Level 32', 'Marketing Level 4', 'Marketing Level 42', 'Material', 'Material2', 'Net due date', 'PH3 Cluster', 'PH3 Cluster2', 'Plant', 'Plant2', 'Posting date', 'Prod.Hier.1', 'Prod.Hier.12', 'Prod.Hier.2', 'Prod.Hier.22', 'Prod.Hier.3', 'Prod.Hier.32', 'Prod.Hier.4', 'Prod.Hier.42', 'Prod.Hier.5', 'Prod.Hier.52', 'Prod.Hier.6', 'Prod.Hier.62', 'Produced Material', 'Produced Material2', 'Region ship-to', 'Region ship-to2', 'Region sold-to', 'Region sold-to2', 'Reporting Unit, book', 'Reporting Unit, book2', 'Risk Class', 'Risk Class2', 'SBE', 'SBE2', 'Sales Organization', 'Sales Organization2', 'Ship-to', 'Ship-to2', 'ShipTo State/ Province', 'ShipTo State/ Province2', 'Sold-to', 'Sold-to2', 'SoldTo State/ Province', 'SoldTo State/ Province2', 'Subregion ship-to', 'Subregion ship-to2', 'Subregion sold-to', 'Subregion sold-to2', 'Unpacked good', 'Unpacked good2', 'KPI AR-KeyDate: Amount in EUR', 'KPI AR-KeyDate: Counter', 'KPI AR-KeyDate: Net Value of Billing Item (DC)', 'KPI AR-KeyDate: Weighted WoC Target days', 'KPI AR-KeyDate: Weighted target days'] | I6: WAT Target; WOC Target; Overdue; Not yet due; % Overdue of Receivables; Receivables; Line items; Net value of billing item; Weighted WoC target days; Weighted target days
A7: AR_PM | B7: pm | F7: Use for receivables performance monitoring over time. Use for EDO (Effective Days Outstanding), WAT Receivables, WDD (Weighted Delay Days), collection effectiveness, payment behavior, performance days, posting days, and deviations against WoC targets. Ideal for working capital performance management and collection trend analysis. | G7: Do not use for current AR balance snapshots, overdue balances, or receivable aging at a key date; use AR-KeyDate instead. Do not use for sales, margin, pricing, shipment, or OTIF analyses. | H7: ['BG, booked', 'BG, booked2', 'Company Code', 'Company Code2', 'Core Business Indicator', 'Core Business Indicator2', 'Country ship-to', 'Country ship-to2', 'Country sold-to', 'Country sold-to2', 'Cust Hier1', 'Cust Hier12', 'Cust Hier2', 'Cust Hier22', 'Cust Hier3', 'Cust Hier32', 'Customer Channel', 'Customer Channel2', 'Customer Cluster', 'Customer Cluster2', 'Extern. Sales Office', 'Extern. Sales Office2', 'FI-ML0', 'FI-ML02', 'Fiscal year/period', 'Fiscal year/period2', 'Int. Sales Group', 'Int. Sales Group2', 'Int. Sales office', 'Int. Sales office2', 'Key Industry', 'Key Industry2', 'Marketing Customer ship-to', 'Marketing Customer ship-to2', 'Marketing Customer sold-to', 'Marketing Customer sold-to2', 'Marketing Level 0', 'Marketing Level 02', 'Marketing Level 1', 'Marketing Level 12', 'Marketing Level 2', 'Marketing Level 22', 'Marketing Level 3', 'Marketing Level 32', 'Marketing Level 4', 'Marketing Level 42', 'Material', 'Material2', 'Net due date', 'PH3 Cluster', 'PH3 Cluster2', 'Plant', 'Plant2', 'Posting date', 'Prod.Hier.1', 'Prod.Hier.12', 'Prod.Hier.2', 'Prod.Hier.22', 'Prod.Hier.3', 'Prod.Hier.32', 'Prod.Hier.4', 'Prod.Hier.42', 'Prod.Hier.5', 'Prod.Hier.52', 'Prod.Hier.6', 'Prod.Hier.62', 'Produced Material', 'Produced Material2', 'Region ship-to', 'Region ship-to2', 'Region sold-to', 'Region sold-to2', 'Reporting Unit, book', 'Reporting Unit, book2', 'Risk Class', 'Risk Class2', 'SBE', 'SBE2', 'Sales Organization', 'Sales Organization2', 'Ship-to', 'Ship-to2', 'ShipTo State/ Province', 'ShipTo State/ Province2', 'Sold-to', 'Sold-to2', 'SoldTo State/ Province', 'SoldTo State/ Province2', 'Subregion ship-to', 'Subregion ship-to2', 'Subregion sold-to', 'Subregion sold-to2', 'Unpacked good', 'Unpacked good2', 'KPI AR-PM: Amount EUR', 'KPI AR-PM: Counter', 'KPI AR-PM: Diff WoC Target', 'KPI AR-PM: EDO (Effective Days Outstanding)', 'KPI AR-PM: Performance Days', 'KPI AR-PM: Posting Days', 'KPI AR-PM: WAT Receivables', 'KPI AR-PM: WDD (Weighted Delay Days)'] | I7: Receivables - PM; Line items - PM; WoC deviation from target; Effective days outstanding; Performance days; Posting days; WAT Receivables; Weighted delay days
A8: COPA | B8: cop | F8: Use for sales and commercial performance analysis. Use for Gross Sales, Net Sales, Net Proceeds, Sales Deductions, Sales Adjustments, Selling Price, price realization, revenue growth, customer/product sales performance, and commercial reporting. Use when the focus is sales value rather than profitability. | G8: Do not use for detailed profitability metrics such as MI1, MI2a, product cost analysis, manufacturing cost analysis, AR reporting, or delivery reliability metrics. Use COSMOS for margin and profitability calculations. | H8: ['BG, booked', 'BG, booked2', 'Company Code', 'Company Code2', 'Core Business Indicator', 'Core Business Indicator2', 'Country ship-to', 'Country ship-to2', 'Country sold-to', 'Country sold-to2', 'Cust Hier1', 'Cust Hier12', 'Cust Hier2', 'Cust Hier22', 'Cust Hier3', 'Cust Hier32', 'Customer Channel', 'Customer Channel2', 'Customer Cluster', 'Customer Cluster2', 'Extern. Sales Office', 'Extern. Sales Office2', 'Fiscal year/period', 'Fiscal year/period2', 'Int. Sales Group', 'Int. Sales Group2', 'Int. Sales office', 'Int. Sales office2', 'Key Industry', 'Key Industry2', 'Marketing Customer ship-to', 'Marketing Customer ship-to2', 'Marketing Customer sold-to', 'Marketing Customer sold-to2', 'Marketing Level 0', 'Marketing Level 02', 'Marketing Level 1', 'Marketing Level 12', 'Marketing Level 2', 'Marketing Level 22', 'Marketing Level 3', 'Marketing Level 32', 'Marketing Level 4', 'Marketing Level 42', 'Material', 'Material2', 'PH3 Cluster', 'PH3 Cluster2', 'Plant', 'Plant2', 'Posting date', 'Prod.Hier.1', 'Prod.Hier.12', 'Prod.Hier.2', 'Prod.Hier.22', 'Prod.Hier.3', 'Prod.Hier.32', 'Prod.Hier.4', 'Prod.Hier.42', 'Prod.Hier.5', 'Prod.Hier.52', 'Prod.Hier.6', 'Prod.Hier.62', 'Produced Material', 'Produced Material2', 'Region ship-to', 'Region ship-to2', 'Region sold-to', 'Region sold-to2', 'Reporting Unit, book', 'Reporting Unit, book2', 'SBE', 'SBE2', 'Sales Organization', 'Sales Organization2', 'Ship-to', 'Ship-to2', 'ShipTo State/ Province', 'ShipTo State/ Province2', 'Sold-to', 'Sold-to2', 'SoldTo State/ Province', 'SoldTo State/ Province2', 'Subregion ship-to', 'Subregion ship-to2', 'Subregion sold-to', 'Subregion sold-to2', 'Unpacked good', 'Unpacked good2', 'KPI COPA: Gross Sales Qty', 'KPI COPA: Gross sales', 'KPI COPA: Net proceeds', 'KPI COPA: Net sales', 'KPI COPA: Sales adjustments', 'KPI COPA: Sales deductions'] | I8: Net Sales Growth (%); Selling Price; Gross sales quantity (CO-PA); Gross sales (CO-PA); Net proceeds (CO-PA); Net sales (CO-PA); Sales adjustments (CO-PA); Sales deductions (CO-PA)
A9: COSMOS | B9: cos | F9: Use for profitability, margin, and cost analysis. Use for MI1, MI2a, MI1 %, MI2a %, MI1 per kg, MI2a per kg, Variable Product Costs, Variable Product Costs per kg, Manufacturing Costs, Net Sales, Gross Sales Qty, Net Proceeds, Exchange Rate Effects, and overall business profitability reporting. This is the primary table for margin management and product profitability analysis. | G9: Do not use for accounts receivable analysis, delivery performance monitoring, shipment execution analysis, or operational logistics KPIs. Do not use when only COPA sales values are required and profitability metrics are not needed. | H9: ['BG, booked', 'BG, booked2', 'Calendar Day', 'Company Code', 'Company Code2', 'Core Business Indicator', 'Core Business Indicator2', 'Country ship-to', 'Country ship-to2', 'Country sold-to', 'Country sold-to2', 'Cust Hier1', 'Cust Hier12', 'Cust Hier2', 'Cust Hier22', 'Cust Hier3', 'Cust Hier32', 'Customer Channel', 'Customer Channel2', 'Customer Cluster', 'Customer Cluster2', 'Exchange rate effect', 'Extern. Sales Office', 'Extern. Sales Office2', 'Fiscal year/period', 'Fiscal year/period2', 'Int. Sales Group', 'Int. Sales Group2', 'Int. Sales office', 'Int. Sales office2', 'Key Industry', 'Key Industry2', 'Marketing Customer ship-to', 'Marketing Customer ship-to2', 'Marketing Customer sold-to', 'Marketing Customer sold-to2', 'Marketing Level 0', 'Marketing Level 02', 'Marketing Level 1', 'Marketing Level 12', 'Marketing Level 2', 'Marketing Level 22', 'Marketing Level 3', 'Marketing Level 32', 'Marketing Level 4', 'Marketing Level 42', 'Material', 'Material2', 'PH3 Cluster', 'PH3 Cluster2', 'Plant', 'Plant2', 'Prod.Hier.1', 'Prod.Hier.12', 'Prod.Hier.2', 'Prod.Hier.22', 'Prod.Hier.3', 'Prod.Hier.32', 'Prod.Hier.4', 'Prod.Hier.42', 'Prod.Hier.5', 'Prod.Hier.52', 'Prod.Hier.6', 'Prod.Hier.62', 'Produced Material', 'Produced Material2', 'Region ship-to', 'Region ship-to2', 'Region sold-to', 'Region sold-to2', 'Reporting Unit, book', 'Reporting Unit, book2', 'SBE', 'SBE2', 'Sales Organization', 'Sales Organization2', 'Ship-to', 'Ship-to2', 'ShipTo State/ Province', 'ShipTo State/ Province2', 'Sold-to', 'Sold-to2', 'SoldTo State/ Province', 'SoldTo State/ Province2', 'Subregion ship-to', 'Subregion ship-to2', 'Subregion sold-to', 'Subregion sold-to2', 'Unpacked good', 'Unpacked good2', 'KPI COSMOS: Consolidated Marginal Income II a', 'KPI COSMOS: Consolidated Marginal Income I', 'KPI COSMOS: Gross Sales', 'KPI COSMOS: Gross Sales Qty (in+ex)', 'KPI COSMOS: Net Proceeds', 'KPI COSMOS: Net Sales', 'KPI COSMOS: Product Costs, Var.', 'KPI COSMOS: Sales Adjustments', 'KPI COSMOS: Sales Deductions', 'KPI COSMOS: Total Manufacturing Costs, Fix'] | I9: Var. Product Costs per kg; MI1 in %; Margin I per kg; MI2a in %; MI2a per kg; Consolidated marginal income I; Consolidated marginal income II a; Gross sales (COSMOS); Gross sales quantity internal + external (COSMOS); Net proceeds (COSMOS); Net sales (COSMOS); Variable product costs; Sales Adjustments (COSMOS); Sales deductions (COSMOS); Total fixed manufacturing costs
A10: OTIF | B10: o | F10: Use for supply chain and customer service performance reporting. Use for OTIF Rate, delivery reliability, on-time delivery, in-full delivery, late deliveries, transportation performance, quantity deviations, overdeliveries, underdeliveries, carrier performance, and logistics service level analysis. | G10: Do not use for sales revenue, profitability, pricing, receivables, working capital, or financial performance reporting. Delivery quantities should be used for service-level analysis only, not official sales volume reporting. | H10: ['Act. GI Day', 'BG, booked', 'BG, booked2', 'Carrier', 'Carrier2', 'Company Code', 'Company Code2', 'Core Business Indicator', 'Core Business Indicator2', 'Country ship-to', 'Country ship-to2', 'Country sold-to', 'Country sold-to2', 'Delivery plant', 'Delivery plant2', 'Extern. Sales Office', 'Extern. Sales Office2', 'Int. Sales Group', 'Int. Sales Group2', 'Int. Sales office', 'Int. Sales office2', 'Key Industry', 'Key Industry2', 'Leg transp. Chain', 'Leg transp. Chain2', 'Loading Country', 'Loading Country2', 'Loading location', 'Loading location2', 'Marketing Customer ship-to', 'Marketing Customer ship-to2', 'Marketing Customer sold-to', 'Marketing Customer sold-to2', 'Marketing Level 0', 'Marketing Level 02', 'Marketing Level 1', 'Marketing Level 12', 'Marketing Level 2', 'Marketing Level 22', 'Marketing Level 3', 'Marketing Level 32', 'Marketing Level 4', 'Marketing Level 42', 'Material', 'Material2', 'Mode of transport', 'Mode of transport2', 'PH3 Cluster', 'PH3 Cluster2', 'Plant', 'Plant2', 'Prod.Hier.1', 'Prod.Hier.12', 'Prod.Hier.2', 'Prod.Hier.22', 'Prod.Hier.3', 'Prod.Hier.32', 'Prod.Hier.4', 'Prod.Hier.42', 'Prod.Hier.5', 'Prod.Hier.52', 'Prod.Hier.6', 'Prod.Hier.62', 'Produced Material', 'Produced Material2', 'Region ship-to', 'Region ship-to2', 'Region sold-to', 'Region sold-to2', 'Reporting Unit, book', 'Reporting Unit, book2', 'SBE', 'SBE2', 'Ship-to', 'Ship-to2', 'ShipTo State/ Province', 'ShipTo State/ Province2', 'Sold-to', 'Sold-to2', 'SoldTo State/ Province', 'SoldTo State/ Province2', 'Subregion ship-to', 'Subregion ship-to2', 'Subregion sold-to', 'Subregion sold-to2', 'T3 Arr. Date planned', 'T3 Arr. date actual', 'T3 Loading Loc. ROI', 'T3 Loading Loc. ROI2', 'T3 SH Shipper', 'T3 SH Shipper2', 'TM Destin. Location', 'TM Destin. Location2', 'Unpacked good', 'Unpacked good2', 'KPI OTIF: # OTIF', 'KPI OTIF: # late GI', 'KPI OTIF: # late IF', 'KPI OTIF: # late NIF', 'KPI OTIF: # late create', 'KPI OTIF: # late transport', 'KPI OTIF: # not in full', 'KPI OTIF: # on time', 'KPI OTIF: # total deliveries', 'KPI OTIF: # total late', 'KPI OTIF: # total late+OT NIF', 'KPI OTIF: 1. Agreed quantity KG', 'KPI OTIF: Delivery Quantity KG', 'KPI OTIF: Overdelivery KG', 'KPI OTIF: Qty deviation KG', 'KPI OTIF: Underdelivery KG', 'KPI OTIF: # OT not in full' ] | I10: OTIF Rate; On-time but incomplete deliveries; OTIF-compliant deliveries; Deliveries with late goods issue; Late and complete deliveries; Late and not-in-full deliveries (NIF); Deliveries with late order creation; Deliveries with transport delay; Incomplete deliveries; On-time deliveries; Total deliveries; Total late deliveries; Total late and/or incomplete deliveries; Agreed delivery quantity; Actually delivered quantity; Overdelivery quantity; Quantity deviation; Underdelivery quantity
A11: Sales | B11: s | F11: Use for order fulfillment, shipment, and delivery volume analysis. Use for Delivery Quantity KG, shipment values, delivery execution, planned vs. actual delivery dates, goods issue tracking, delivery trends, and Volume Growth (%). This table is best for operational sales volume and logistics execution reporting. | G11: Do not use for profitability calculations, marginal income reporting, receivables analysis, pricing calculations, or OTIF service-level calculations. For revenue use COPA; for margin use COSMOS; for delivery reliability use OTIF. | H11: ['Act. GI Day', 'Actual delivery date', 'BG, booked', 'BG, booked2', 'Company Code', 'Company Code2', 'Core Business Indicator', 'Core Business Indicator2', 'Country ship-to', 'Country ship-to2', 'Country sold-to', 'Country sold-to2', 'Created on', 'Cust Hier1', 'Cust Hier12', 'Cust Hier2', 'Cust Hier22', 'Cust Hier3', 'Cust Hier32', 'Customer Cluster', 'Customer Cluster2', 'Delivery date plann.', 'Document currency', 'Document currency2', 'Extern. Sales Office', 'Extern. Sales Office2', 'Int. Sales Group', 'Int. Sales Group2', 'Int. Sales office', 'Int. Sales office2', 'Key Industry', 'Key Industry2', 'Marketing Customer ship-to', 'Marketing Customer ship-to2', 'Marketing Customer sold-to', 'Marketing Customer sold-to2', 'Marketing Level 0', 'Marketing Level 02', 'Marketing Level 1', 'Marketing Level 12', 'Marketing Level 2', 'Marketing Level 22', 'Marketing Level 3', 'Marketing Level 32', 'Marketing Level 4', 'Marketing Level 42', 'Material', 'Material2', 'PH3 Cluster', 'PH3 Cluster2', 'Plan. goods is. date', 'Plant', 'Plant2', 'Prod.Hier.1', 'Prod.Hier.12', 'Prod.Hier.2', 'Prod.Hier.22', 'Prod.Hier.3', 'Prod.Hier.32', 'Prod.Hier.4', 'Prod.Hier.42', 'Prod.Hier.5', 'Prod.Hier.52', 'Prod.Hier.6', 'Prod.Hier.62', 'Prod.Hier.622', 'Prod.Hier.6222', 'Produced Material', 'Produced Material2', 'Region ship-to', 'Region ship-to2', 'Region sold-to', 'Region sold-to2', 'Reporting Unit, book', 'Reporting Unit, book2', 'SBE', 'SBE2', 'Ship-to', 'Ship-to2', 'ShipTo State/ Province', 'ShipTo State/ Province2', 'Sold-to', 'Sold-to2', 'SoldTo State/ Province', 'SoldTo State/ Province2', 'Subregion ship-to', 'Subregion ship-to2', 'Subregion sold-to', 'Subregion sold-to2', 'Unpacked good', 'Unpacked good2', 'KPI Sales: Delivery Quantity KG', 'KPI Sales: Net value deliv. DC', 'KPI Sales: Net value delivery EUR'] | I11: Volume Growth (%); Order Volume; Net value of delivery item; Net value of delivery
A12: Covestro | B12: Deloitte FDE
A13: Fields to be clarified - High priority | B13: Fields to be clarified - High priority
A14: Fields to be clarified - Mid priority | B14: Fields to be clarified - Mid priority
A15: Fields to be clarified - Low priority | B15: Fields to be clarified - Low priority
A17: 🟡 Yellow rows = example data from product reference model. Replace with your client's actual table names, descriptions and business rules before use.

Sheet 3. Column Info
A1: COLUMN INFO
A2: One row per column in each table. Defines business meaning, data type, and the natural-language aliases the AI uses to map user questions to the right column.
A3: ℹ Instructions: Add one row per column per table. business_name = plain English label shown in responses. friendly_names = comma-separated phrases users might say (e.g. 'revenue, sales, net revenue'). The AI uses friendly_names to resolve ambiguous questions — the more you add, the more accurate it is. is_key = TRUE for primary/foreign keys. is_required = TRUE if the column is always populated.
A5: table_name | B5: column_name | C5: technical_name | D5: business_name | E5: description | F5: data_type | G5: is_key | H5: is_required | I5: sample_values | J5: notes | K5: friendly_names
A6: AR_KeyDate | B6: BG, booked | C6: BG__BOOKED | D6: Booked business group | E6: Indicator for the booked business group (BG) of a document. Used in profitability analysis (CO-PA) and reporting to delimit booking units within a company code. | F6: NUMBER(2) | H6: False | I6: 70 | J6: NOT NULL, integer only, max abs value 97 | K6: business group; booked business group; BG; business unit group; reporting business group
A7: AR_KeyDate | B7: BG, booked2 | C7: BG__BOOKED2 | D7: Booked business group (TEXT) | F7: VARCHAR2(40) | H7: False | I7: PM | J7: NOT NULL, text/mixed, max length 20
A8: AR_KeyDate | B8: Company Code | C8: COMPANY_CODE | D8: Company code | E8: A company code is the smallest organizational unit for which a complete, self-contained set of accounts can be drawn up. It typically corresponds to a legally independent company within the group. All documents are assigned to a company code. Each legal entity has its own company code. | F8: NUMBER(4) | H8: False | I8: 889 | J8: NOT NULL, integer only, max abs value 2422 | K8: company; legal entity; entity; subsidiary; business entity; reporting company
A9: AR_KeyDate | B9: Company Code2 | C9: COMPANY_CODE2 | D9: Company code (TEXT) | F9: VARCHAR2(40) | H9: False | I9: Covestro Private/Ind | J9: NOT NULL, text/mixed, max length 20
A10: AR_KeyDate | B10: Core Business Indicator | C10: CORE_BUSINESS_INDICATOR | D10: Core business indicator | E10: A flag that indicates whether a business transaction belongs to company' s core business or is assigned to a sideline business. Relevant for separating core and non-core activities in reporting. Values C, P, and T together represent Core Business classification. | F10: VARCHAR2(2) | H10: False | I10: C | J10: NOT NULL, text/mixed, max length 1 | K10: core business; non-core business; business classification; core activity; strategic business flag
A11: AR_KeyDate | B11: Core Business Indicator2 | C11: CORE_BUSINESS_INDICATOR2 | D11: Core business indicator (TEXT) | F11: VARCHAR2(40) | H11: False | I11: Core external market | J11: NOT NULL, text/mixed, max length 20
A12: AR_KeyDate | B12: Country ship-to | C12: COUNTRY_SHIP_TO | D12: Country of the ship-to party | E12: The country of the ship-to partner (goods recipient) from the customer master. Used for geographic analyses, foreign trade statistics and export controls. Part of the customer attributes in SAP S/4HANA (Ship-to Country). | F12: VARCHAR2(4) | H12: False | I12: IN | J12: NOT NULL, text/mixed, max length 2 | K12: ship-to country; delivery country; destination country; receiving country; customer destination country
A13: AR_KeyDate | B13: Country ship-to2 | C13: COUNTRY_SHIP_TO2 | D13: Country of the ship-to party (TEXT) | F13: VARCHAR2(28) | H13: False | I13: India | J13: NOT NULL, text/mixed, max length 14
A14: AR_KeyDate | B14: Country sold-to | C14: COUNTRY_SOLD_TO | D14: Country of the sold-to party | E14: The country of the sold-to partner (ordering customer) from the customer master. Used for geographic sales analyses. Part of the customer attributes in SAP S/4HANA (Sold-to Country). | F14: VARCHAR2(4) | H14: False | I14: IN | J14: NOT NULL, text/mixed, max length 2 | K14: customer country; sold-to country; sales country; ordering country; market country
A15: AR_KeyDate | B15: Country sold-to2 | C15: COUNTRY_SOLD_TO2 | D15: Country of the sold-to party (TEXT) | F15: VARCHAR2(30) | H15: False | I15: India | J15: NOT NULL, text/mixed, max length 15
A16: AR_KeyDate | B16: Cust Hier1 | C16: CUST_HIER1 | D16: Customer hierarchy level 1 | E16: The highest level of the customer hierarchy. Customer hierarchies are flexible, multi-level structures that reflect the organizational structure of customers. Level 1 typically represents the parent company (e.g. group headquarters). Used for pricing and reporting. | F16: VARCHAR2(4) | H16: False | I16: 33 | J16: NOT NULL, text/mixed, max length 2 | K16: customer hierarchy level 1; parent customer; global parent; customer group level 1; top customer hierarchy
A17: AR_KeyDate | B17: Cust Hier12 | C17: CUST_HIER12 | D17: Customer hierarchy level 1 (TEXT) | F17: VARCHAR2(38) | H17: False | I17: TUR PU Specialties | J17: NOT NULL, text/mixed, max length 19
A18: AR_KeyDate | B18: Cust Hier2 | C18: CUST_HIER2 | D18: Customer hierarchy level 2 | E18: Second level of the customer hierarchy. Typically represents an intermediate level (e.g. regional subsidiary) within the customer hierarchy. | F18: VARCHAR2(6) | H18: False | I18: 604 | J18: NOT NULL, text/mixed, max length 3 | K18: customer hierarchy level 2; customer group level 2; regional customer group; hierarchy level 2
A19: AR_KeyDate | B19: Cust Hier22 | C19: CUST_HIER22 | D19: Customer hierarchy level 2 (TEXT) | F19: VARCHAR2(40) | H19: False | I19: TUR Auto | J19: NOT NULL, text/mixed, max length 20
A20: AR_KeyDate | B20: Cust Hier3 | C20: CUST_HIER3 | D20: Customer hierarchy level 3 | E20: Third level of the customer hierarchy. Represents the lowest standard hierarchy level (e.g. individual branch or subsidiary of the customer). | F20: VARCHAR2(10) | H20: False | I20: 71008 | J20: NOT NULL, text/mixed, max length 5 | K20: customer hierarchy level 3; customer group level 3; local customer group; hierarchy level 3
A21: AR_KeyDate | B21: Cust Hier32 | C21: CUST_HIER32 | D21: Customer hierarchy level 3 (TEXT) | F21: VARCHAR2(40) | H21: False | I21: TU Auto LoadFloorSpr | J21: NOT NULL, text/mixed, max length 20
A22: AR_KeyDate | B22: Customer Channel | C22: CUSTOMER_CHANNEL | D22: Customer sales channel | E22: An attribute that classifies a customer's sales channel(e.g. direct sales, distributor, e-commerce). Used for segmentation and sales analyses in BW reporting. | F22: VARCHAR2(6) | H22: False | I22: D01 | J22: NOT NULL, text/mixed, max length 3 | K22: sales channel; customer channel; distribution channel; route to market; go-to-market channel
A23: AR_KeyDate | B23: Customer Channel2 | C23: CUSTOMER_CHANNEL2 | D23: Customer sales channel (TEXT) | F23: VARCHAR2(56) | H23: False | I23: DIR-Direct | J23: NOT NULL, text/mixed, max length 28
A24: AR_KeyDate | B24: Customer Cluster | C24: CUSTOMER_CLUSTER | D24: Customer cluster | E24: An attribute for grouping customers by strategic or analytical criteria (e.g. size, potential, industry). Used in sales controlling and segmentation analysis. | F24: VARCHAR2(8) | H24: False | I24: 1312 | J24: NOT NULL, text/mixed, max length 4 | K24: customer segment; customer cluster; customer category; strategic segment; customer grouping
A25: AR_KeyDate | B25: Customer Cluster2 | C25: CUSTOMER_CLUSTER2 | D25: Customer cluster (TEXT) | F25: VARCHAR2(74) | H25: False | I25: PMC-TUR-SPEC-Others | J25: NOT NULL, text/mixed, max length 37
A26: AR_KeyDate | B26: Extern. Sales Office | C26: EXTERN__SALES_OFFICE | D26: External sales office code | E26: The external sales office is an organizational unit within the sales organization representing geographic sales regions.The nomenclature contains a 2-digit legal entity identifier followed by a number (70–79). Serves as a selection criterion for sales documents and analyses. | F26: VARCHAR2(12) | H26: False | I26: HKA086 | J26: NOT NULL, text/mixed, max length 6 | K26: sales office; external sales office; regional sales office; commercial office
A27: AR_KeyDate | B27: Extern. Sales Office2 | C27: EXTERN__SALES_OFFICE2 | D27: External sales office code (TEXT) | F27: VARCHAR2(40) | H27: False | I27: MBDNO | J27: NOT NULL, text/mixed, max length 20
A28: AR_KeyDate | B28: FI-ML0 | C28: FI_ML0 | D28: Financial characteristic level 0 | E28: An internal characteristic from financial accounting (FI) representing a top-level classification (Level 0) for cross-company-code analyses. Used in integrated financial and management reporting. | F28: NUMBER(2) | H28: False | I28: 71 | J28: NOT NULL, integer only, max abs value 78 | K28: financial hierarchy; finance level 0; finance segment; reporting hierarchy
A29: AR_KeyDate | B29: FI-ML02 | C29: FI_ML02 | D29: Financial characteristic level 0 (TEXT) | F29: VARCHAR2(16) | H29: False | I29: TUR | J29: NOT NULL, text/mixed, max length 8
A30: AR_KeyDate | B30: Fiscal year/period | C30: FISCAL_YEAR_PERIOD | D30: Fiscal year / period | E30: Combination of fiscal year (e.g. 2025) and posting period (e.g. 001–012 for months). Serves as the time dimension in all SAP posting and controlling reports. | F30: NUMBER(10,4) | H30: False | I30: 12.026 | J30: NOT NULL, numeric, max prec/scale 10/4 | K30: fiscal period; fiscal month; accounting period; reporting period; fiscal year; period
A31: AR_KeyDate | B31: Fiscal year/period2 | C31: FISCAL_YEAR_PERIOD2 | D31: Fiscal year / period (TEXT) | F31: VARCHAR2(28) | H31: False | I31: Jan 26 | J31: NOT NULL, text/mixed, max length 14
A32: AR_KeyDate | B32: Int. Sales Group | C32: INT__SALES_GROUP | D32: Internal sales group | E32: An internal sales group is a sub-unit of a sales office. Employees are assigned to sales groups; a group is responsible for all line items in a sales document. | F32: VARCHAR2(6) | H32: False | I32: 0B0 | J32: NOT NULL, text/mixed, max length 3 | K32: sales group; internal sales group; sales team; commercial group
A33: AR_KeyDate | B33: Int. Sales Group2 | C33: INT__SALES_GROUP2 | D33: Internal sales group (TEXT) | F33: VARCHAR2(34) | H33: False | I33: MBVPR | J33: NOT NULL, text/mixed, max length 17
A34: AR_KeyDate | B34: Key Industry | C34: KEY_INDUSTRY | D34: Key industry | E34: An attribute that classifies the target industry of a customer or product (e.g. Automotive, Construction, Electronics). Used for market and industry segmentation in sales reporting. | F34: NUMBER(2) | H34: False | I34: 1 | J34: NOT NULL, integer only, max abs value 16 | K34: industry; industry segment; customer industry; market industry; sector
A35: AR_KeyDate | B35: Key Industry2 | C35: KEY_INDUSTRY2 | D35: Key industry (TEXT) | F35: VARCHAR2(40) | H35: False | I35: Automotive | J35: NOT NULL, text/mixed, max length 20
A36: AR_KeyDate | B36: Marketing Customer ship-to | C36: MARKETING_CUSTOMER_SHIP_TO | D36: Marketing customer (ship-to) | E36: An attribute in the customer master that assigns the ship-to party to a higher-level marketing customer. | F36: VARCHAR2(16) | H36: False | I36: 3530369 | J36: NOT NULL, text/mixed, max length 8 | K36: marketing customer ship-to; customer group ship-to; strategic ship-to customer
A37: AR_KeyDate | B37: Marketing Customer ship-to2 | C37: MARKETING_CUSTOMER_SHIP_TO2 | D37: Marketing customer (ship-to) (TEXT) | F37: VARCHAR2(70) | H37: False | I37: SUPREME NONWOVEN INDUSTRIES PVT.LTD | J37: NOT NULL, text/mixed, max length 35
A38: AR_KeyDate | B38: Marketing Customer sold-to | C38: MARKETING_CUSTOMER_SOLD_TO | D38: Marketing customer (sold-to) | E38: An attribute in the customer master that assigns the sold-to party to a higher-level marketing customer. | F38: VARCHAR2(16) | H38: False | I38: 3530369 | J38: NOT NULL, text/mixed, max length 8 | K38: marketing customer; global customer; strategic customer; corporate customer; parent customer
A39: AR_KeyDate | B39: Marketing Customer sold-to2 | C39: MARKETING_CUSTOMER_SOLD_TO2 | D39: Marketing customer (sold-to) (TEXT) | F39: VARCHAR2(70) | H39: False | I39: SUPREME NONWOVEN INDUSTRIES PVT.LTD | J39: NOT NULL, text/mixed, max length 35
A40: AR_KeyDate | B40: Marketing Level 0 | C40: MARKETING_LEVEL_0 | D40: Marketing level 0 (top level) | E40: Highest level of the internal marketing hierarchy. Typically corresponds to the reportable segment (e.g. "Performance Materials" or "Solutions & Specialties"). Serves as the highest aggregation level in product portfolio reporting. | F40: VARCHAR2(4) | H40: False | I40: 71 | J40: NOT NULL, text/mixed, max length 2 | K40: business segment; top marketing hierarchy; strategic segment; portfolio segment
A41: AR_KeyDate | B41: Marketing Level 02 | C41: MARKETING_LEVEL_02 | D41: Marketing level 0 (top level) (TEXT) | F41: VARCHAR2(16) | H41: False | I41: TUR | J41: NOT NULL, text/mixed, max length 8
A42: AR_KeyDate | B42: Marketing Level 1 | C42: MARKETING_LEVEL_1 | D42: Marketing level 1 | E42: Second level of the internal marketing hierarchy. Subdivides the reportable segment into strategic product groups or business entities. | F42: VARCHAR2(6) | H42: False | I42: P71 | J42: NOT NULL, text/mixed, max length 3 | K42: marketing hierarchy level 1; business line; marketing portfolio level 1
A43: AR_KeyDate | B43: Marketing Level 12 | C43: MARKETING_LEVEL_12 | D43: Marketing level 1 (TEXT) | F43: VARCHAR2(40) | H43: False | I43: TUR PU Specialties | J43: NOT NULL, text/mixed, max length 20
A44: AR_KeyDate | B44: Marketing Level 2 | C44: MARKETING_LEVEL_2 | D44: Marketing level 2 | E44: Third level of the internal marketing hierarchy. Represents a further subdivision of Marketing Level 1 groups, e.g. by product lines or application areas. | F44: VARCHAR2(6) | H44: False | I44: 714 | J44: NOT NULL, text/mixed, max length 3 | K44: marketing hierarchy level 2; product line; market segment
A45: AR_KeyDate | B45: Marketing Level 22 | C45: MARKETING_LEVEL_22 | D45: Marketing level 2 (TEXT) | F45: VARCHAR2(40) | H45: False | I45: TUR Auto | J45: NOT NULL, text/mixed, max length 20
A46: AR_KeyDate | B46: Marketing Level 3 | C46: MARKETING_LEVEL_3 | D46: Marketing level 3 | E46: Fourth level of the internal marketing hierarchy. Further detail breakdown below Marketing Level 2, e.g. by product types or market segments. | F46: VARCHAR2(6) | H46: False | I46: 201 | J46: NOT NULL, text/mixed, max length 3 | K46: marketing hierarchy level 3; product segment; business segment
A47: AR_KeyDate | B47: Marketing Level 32 | C47: MARKETING_LEVEL_32 | D47: Marketing level 3 (TEXT) | F47: VARCHAR2(40) | H47: False | I47: TU Auto Sys Int APAC | J47: NOT NULL, text/mixed, max length 20
A48: AR_KeyDate | B48: Marketing Level 4 | C48: MARKETING_LEVEL_4 | D48: Marketing level 4 (lowest level) | E48: Lowest level of the internal marketing hierarchy. Represents the most granular classification in the marketing product tree, e.g. individual product grades or specifications. | F48: VARCHAR2(8) | H48: False | I48: A923 | J48: NOT NULL, text/mixed, max length 4 | K48: marketing hierarchy level 4; product group; product specification; portfolio detail
A49: AR_KeyDate | B49: Marketing Level 42 | C49: MARKETING_LEVEL_42 | D49: Marketing level 4 (lowest level) (TEXT) | F49: VARCHAR2(40) | H49: False | I49: TU Auto LoadFloorSpr | J49: NOT NULL, text/mixed, max length 20
A50: AR_KeyDate | B50: Material | C50: MATERIAL | D50: Material number | E50: The unique alphanumeric identifier of a material (product, raw material, semi-finished good) in the SAP system. Central master data object to which all logistical and accounting transactions are assigned. | F50: VARCHAR2(16) | H50: False | I50: 730525 | J50: NOT NULL, text/mixed, max length 8 | K50: product number; material; SKU; item number; article; product code
A51: AR_KeyDate | B51: Material2 | C51: MATERIAL2 | D51: Material number (TEXT) | F51: VARCHAR2(80) | H51: False | I51: DESMODUR VP.PU 1511 L 0250,00 KG B13 | J51: NOT NULL, text/mixed, max length 40
A52: AR_KeyDate | B52: Net due date | C52: NET_DUE_DATE | D52: Net due date | E52: The date on which an open receivable (customer line item) is due net without any deduction. Derived from the invoice date plus the agreed payment terms. Central to accounts receivable management and WoC/EDO KPIs. | F52: DATE | H52: False | I52: 16.02.2026 | J52: NOT NULL, all non-empty values match date pattern | K52: due date; payment due date; receivable due date; invoice due date
A53: AR_KeyDate | B53: PH3 Cluster | C53: PH3_CLUSTER | D53: Product hierarchy level 3 cluster | E53: A grouping based on the third product hierarchy level (PH3). Aggregates product groups into strategic clusters used for sales and planning analyses. Example cluster: ACR for acrylate product groups. | F53: VARCHAR2(10) | H53: False | I53: 70630 | J53: NOT NULL, text/mixed, max length 5 | K53: product cluster; product group; product segment; product portfolio cluster
A54: AR_KeyDate | B54: PH3 Cluster2 | C54: PH3_CLUSTER2 | D54: Product hierarchy level 3 cluster (TEXT) | F54: VARCHAR2(40) | H54: False | I54: SMDI | J54: NOT NULL, text/mixed, max length 20
A55: AR_KeyDate | B55: Plant | C55: PLANT | D55: Plant | E55: A plant is an organizational unit within logistics that represents the location of a production facility, storage location or service provision. All material stocks, production orders and deliveries are assigned to a plant. | F55: VARCHAR2(8) | H55: False | I55: I1AQ | J55: NOT NULL, text/mixed, max length 4 | K55: plant; factory; manufacturing site; production site; warehouse; location
A56: AR_KeyDate | B56: Plant2 | C56: PLANT2 | D56: Plant (TEXT) | F56: VARCHAR2(40) | H56: False | I56: DC NEW RHENUS WAREHO | J56: NOT NULL, text/mixed, max length 20
A57: AR_KeyDate | B57: Posting date | C57: POSTING_DATE | D57: Posting date | E57: The date on which an accounting document is posted in the system. Determines the assignment to the posting period and fiscal year. May differ from the document date (invoice date). | F57: DATE | H57: False | I57: 02.01.2026 | J57: NOT NULL, all non-empty values match date pattern | K57: accounting date; posting date; booking date; financial posting date
A58: AR_KeyDate | B58: Prod.Hier.1 | C58: PROD_HIER_1 | D58: Product hierarchy level 1 | E58: First (highest) level of the product hierarchy used for high-level product grouping. An alphanumeric character string that groups materials by overarching characteristics (e.g. product division). | F58: VARCHAR2(4) | H58: False | I58: 70 | J58: NOT NULL, text/mixed, max length 2 | K58: product hierarchy; product family; product division
A59: AR_KeyDate | B59: Prod.Hier.12 | C59: PROD_HIER_12 | D59: Product hierarchy level 1 (TEXT) | F59: VARCHAR2(30) | H59: False | I59: PM | J59: NOT NULL, text/mixed, max length 15
A60: AR_KeyDate | B60: Prod.Hier.2 | C60: PROD_HIER_2 | D60: Product hierarchy level 2 | E60: Second level of the product hierarchy. Subdivides the first level into product categories. | F60: VARCHAR2(4) | H60: False | I60: 4 | J60: NOT NULL, text/mixed, max length 2 | K60: product category; product line; product hierarchy level 2
A61: AR_KeyDate | B61: Prod.Hier.22 | C61: PROD_HIER_22 | D61: Product hierarchy level 2 (TEXT) | F61: VARCHAR2(40) | H61: False | I61: MDI PM | J61: NOT NULL, text/mixed, max length 20
A62: AR_KeyDate | B62: Prod.Hier.3 | C62: PROD_HIER_3 | D62: Product hierarchy level 3 | E62: Third level of the product hierarchy. Represents the product subcategory or product type. | F62: VARCHAR2(6) | H62: False | I62: 100 | J62: NOT NULL, text/mixed, max length 3 | K62: product type; product subgroup; hierarchy level 3
A63: AR_KeyDate | B63: Prod.Hier.32 | C63: PROD_HIER_32 | D63: Product hierarchy level 3 (TEXT) | F63: VARCHAR2(40) | H63: False | I63: MDI PM POLYMER | J63: NOT NULL, text/mixed, max length 20
A64: AR_KeyDate | B64: Prod.Hier.4 | C64: PROD_HIER_4 | D64: Product hierarchy level 4 | E64: Fourth level of the product hierarchy used for more detailed product classifications. | F64: VARCHAR2(6) | H64: False | I64: 172 | J64: NOT NULL, text/mixed, max length 3 | K64: product classification; product segment; hierarchy level 4
A65: AR_KeyDate | B65: Prod.Hier.42 | C65: PROD_HIER_42 | D65: Product hierarchy level 4 (TEXT) | F65: VARCHAR2(40) | H65: False | I65: pMDI | J65: NOT NULL, text/mixed, max length 20
A66: AR_KeyDate | B66: Prod.Hier.5 | C66: PROD_HIER_5 | D66: Product hierarchy level 5 | E66: Fifth level of the product hierarchy used for more granular product group analyses (not used anymore) | F66: VARCHAR2(2) | H66: False | I66: # | J66: NOT NULL, text/mixed, max length 1 | K66: detailed product group; hierarchy level 5; fifth-level product grouping
A67: AR_KeyDate | B67: Prod.Hier.52 | C67: PROD_HIER_52 | D67: Product hierarchy level 5 (TEXT) | F67: VARCHAR2(40) | H67: False | I67: 70/04/100/172/Not as | J67: NOT NULL, text/mixed, max length 20
A68: AR_KeyDate | B68: Prod.Hier.6 | C68: PROD_HIER_6 | D68: Product hierarchy level 6 | E68: Sixth and lowest level of the product hierarchy at individual product or grade level for detailed product reporting. (not used anymore) | F68: VARCHAR2(2) | H68: False | I68: # | J68: NOT NULL, text/mixed, max length 1 | K68: product grade; SKU hierarchy; detailed product hierarchy
A69: AR_KeyDate | B69: Prod.Hier.62 | C69: PROD_HIER_62 | D69: Product hierarchy level 6 (TEXT) | F69: VARCHAR2(40) | H69: False | I69: 70/04/100/172/Not as | J69: NOT NULL, text/mixed, max length 20
A70: AR_KeyDate | B70: Produced Material | C70: PRODUCED_MATERIAL | D70: Produced material | E70: The material actually produced (finished product or semi-finished good) in the production process. May differ from the sold material (e.g. in case of repackaging or kitting). Relevant in the COSMOS consolidation process for the assignment of production costs. Remark: not all materials are assigned to a produced material (specific for certain business entities only) | F70: VARCHAR2(36) | H70: False | I70: 4203380 | J70: NOT NULL, text/mixed, max length 18 | K70: produced material; manufactured product; production material; made product
A71: AR_KeyDate | B71: Produced Material2 | C71: PRODUCED_MATERIAL2 | D71: Produced material (TEXT) | F71: VARCHAR2(80) | H71: False | I71: MDI 44 V 20 L | J71: NOT NULL, text/mixed, max length 40
A72: AR_KeyDate | B72: Region ship-to | C72: REGION_SHIP_TO | D72: Region of the ship-to party | E72: The geographic region (e.g. state, province) of the ship-to party. Derived from the customer address master and used for regional sales analyses. | F72: VARCHAR2(4) | H72: False | I72: R3 | J72: NOT NULL, text/mixed, max length 2 | K72: ship-to region; delivery region; destination region; customer delivery region; geography ship to; geographic region ship to; area ship to
A73: AR_KeyDate | B73: Region ship-to2 | C73: REGION_SHIP_TO2 | D73: Region of the ship-to party (TEXT) | F73: VARCHAR2(24) | H73: False | I73: APAC | J73: NOT NULL, text/mixed, max length 12
A74: AR_KeyDate | B74: Region sold-to | C74: REGION_SOLD_TO | D74: Region of the sold-to party | E74: The geographic region of the sold-to party. Derived from the customer address master and used for regional sales analyses. | F74: VARCHAR2(4) | H74: False | I74: R3 | J74: NOT NULL, text/mixed, max length 2 | K74: sales region; customer region; market region; sold-to region; geography sold to; geographic region sold to; area sold to
A75: AR_KeyDate | B75: Region sold-to2 | C75: REGION_SOLD_TO2 | D75: Region of the sold-to party (TEXT) | F75: VARCHAR2(24) | H75: False | I75: APAC | J75: NOT NULL, text/mixed, max length 12
A76: AR_KeyDate | B76: Reporting Unit, book | C76: REPORTING_UNIT__BOOK | D76: Reporting unit (booked) | E76: The reporting unit identical to the profit center (1:1 relationship). It serves as the reporting entity in internal and external reporting. Booked refers to the actual profit center assignment recorded at posting time. Reporting units are part of the SBE hierarchy in the profit center standard hierarchy tree. | F76: VARCHAR2(12) | H76: False | I76: 630 | J76: NOT NULL, text/mixed, max length 6 | K76: reporting unit; profit center; reporting entity; business reporting unit
A77: AR_KeyDate | B77: Reporting Unit, book2 | C77: REPORTING_UNIT__BOOK2 | D77: Reporting unit (booked) (TEXT) | F77: VARCHAR2(40) | H77: False | I77: MDI | J77: NOT NULL, text/mixed, max length 20
A78: AR_KeyDate | B78: Risk Class | C78: RISK_CLASS | D78: Risk class | E78: Subordinate classification within a risk category. Indicates the severity or probability of occurrence of a risk. Used in the ICS and risk management process to prioritize control measures. | F78: VARCHAR2(2) | H78: False | I78: N | J78: NOT NULL, text/mixed, max length 1 | K78: risk classification; customer risk class; credit risk class; risk level
A79: AR_KeyDate | B79: Risk Class2 | C79: RISK_CLASS2 | D79: Risk class (TEXT) | F79: VARCHAR2(44) | H79: False | I79: New customer | J79: NOT NULL, text/mixed, max length 22
A80: AR_KeyDate | B80: SBE | C80: SBE | D80: Strategic Business Entity | E80: A Strategic Business Entity (SBE) is a higher-level organizational unit that fulfills at least the criteria for a profit center and additionally has significant independence from other SBEs (own production, marketing, R&D, dedicated assets). SBEs are part of the profit center standard hierarchy tree and are typically equated with "Strategic Planning Unit" or "Cash Generating Unit". Formal approval by Controlling, Strategy and Accounting is required. | F80: VARCHAR2(4) | H80: False | I80: 04 | J80: NOT NULL, text/mixed, max length 2 | K80: strategic business entity; business unit; operating segment; strategic unit
A81: AR_KeyDate | B81: SBE2 | C81: SBE2 | D81: Strategic Business Entity (TEXT) | F81: VARCHAR2(64) | H81: False | I81: SMDI | J81: NOT NULL, text/mixed, max length 32
A82: AR_KeyDate | B82: Sales Organization | C82: SALES_ORGANIZATION | D82: Sales organization | E82: The sales organization is the highest aggregation level for sales statistics in SAP SD. It is assigned to exactly one company code. All line items of a sales, delivery or billing document belong to a sales organization. Nomenclature begins with a 2-digit legal entity identifier; sideline organizations end with "98". | F82: VARCHAR2(8) | H82: False | I82: I120 | J82: NOT NULL, text/mixed, max length 4 | K82: sales organization; sales org; selling entity; commercial organization
A83: AR_KeyDate | B83: Sales Organization2 | C83: SALES_ORGANIZATION2 | D83: Sales organization (TEXT) | F83: VARCHAR2(40) | H83: False | I83: Covestro (IN) Ltd. | J83: NOT NULL, text/mixed, max length 20
A84: AR_KeyDate | B84: Ship-to | C84: SHIP_TO | D84: Ship-to party | E84: The partner to whom goods are physically delivered (partner function SH). May differ from the sold-to party. Delivery address, shipping conditions and goods recipient data are taken from the customer master. | F84: VARCHAR2(16) | H84: False | I84: 11532198 | J84: NOT NULL, text/mixed, max length 8 | K84: ship-to customer; consignee; delivery customer; receiving customer; recipient
A85: AR_KeyDate | B85: Ship-to2 | C85: SHIP_TO2 | D85: Ship-to party (TEXT) | F85: VARCHAR2(70) | H85: False | I85: SUPREME TREON PRIVATE LIMITED | J85: NOT NULL, text/mixed, max length 35
A86: AR_KeyDate | B86: ShipTo State/ Province | C86: SHIPTO_STATE__PROVINCE | D86: State / province of the ship-to party | E86: The state or province of the ship-to party from the address master. Relevant for tax assignments (e.g. US sales tax) and regional analyses. | F86: VARCHAR2(12) | H86: False | I86: IN/MH | J86: NOT NULL, text/mixed, max length 6 | K86: ship-to state; delivery state; destination province; delivery region
A87: AR_KeyDate | B87: ShipTo State/ Province2 | C87: SHIPTO_STATE__PROVINCE2 | D87: State / province of the ship-to party (TEXT) | F87: VARCHAR2(40) | H87: False | I87: Maharashtra | J87: NOT NULL, text/mixed, max length 20
A88: AR_KeyDate | B88: Sold-to | C88: SOLD_TO | D88: Sold-to party | E88: The customer who places the order (partner function SP). Central business partner in the order-to-cash process. Pricing conditions, payment terms and customer hierarchies are derived from the sold-to party. | F88: VARCHAR2(16) | H88: False | I88: 11532198 | J88: NOT NULL, text/mixed, max length 8 | K88: customer; customer name; client; client name; account; ordering customer; sold-to customer
A89: AR_KeyDate | B89: Sold-to2 | C89: SOLD_TO2 | D89: Sold-to party (TEXT) | F89: VARCHAR2(70) | H89: False | I89: SUPREME TREON PRIVATE LIMITED | J89: NOT NULL, text/mixed, max length 35
A90: AR_KeyDate | B90: SoldTo State/ Province | C90: SOLDTO_STATE__PROVINCE | D90: State / province of the sold-to party | E90: The state or province of the sold-to party from the address master. Relevant for tax and regional analyses. | F90: VARCHAR2(12) | H90: False | I90: MH | J90: NOT NULL, text/mixed, max length 6 | K90: customer state; sold-to state; customer province; sales province
A91: AR_KeyDate | B91: SoldTo State/ Province2 | C91: SOLDTO_STATE__PROVINCE2 | D91: State / province of the sold-to party (TEXT) | F91: VARCHAR2(40) | H91: False | I91: Maharashtra | J91: NOT NULL, text/mixed, max length 20
A92: AR_KeyDate | B92: Subregion ship-to | C92: SUBREGION_SHIP_TO | D92: Subregion of the ship-to party | E92: An attribute that assigns the ship-to party to a geographic subregion below the main region (e.g. Eastern Europe as a subregion of Europe). Used for detailed geographic sales analyses. | F92: VARCHAR2(6) | H92: False | I92: R34 | J92: NOT NULL, text/mixed, max length 3 | K92: ship-to subregion; delivery subregion; destination subregion
A93: AR_KeyDate | B93: Subregion ship-to2 | C93: SUBREGION_SHIP_TO2 | D93: Subregion of the ship-to party (TEXT) | F93: VARCHAR2(40) | H93: False | I93: INDIA SUBCONTINENT | J93: NOT NULL, text/mixed, max length 20
A94: AR_KeyDate | B94: Subregion sold-to | C94: SUBREGION_SOLD_TO | D94: Subregion of the sold-to party | E94: An attribute that assigns the sold-to party to a geographic subregion. Analogous to Subregion ship-to, but referring to the sold-to party. | F94: VARCHAR2(6) | H94: False | I94: R34 | J94: NOT NULL, text/mixed, max length 3 | K94: sales subregion; customer subregion; market subregion
A95: AR_KeyDate | B95: Subregion sold-to2 | C95: SUBREGION_SOLD_TO2 | D95: Subregion of the sold-to party (TEXT) | F95: VARCHAR2(40) | H95: False | I95: INDIA SUBCONTINENT | J95: NOT NULL, text/mixed, max length 20
A96: AR_KeyDate | B96: Unpacked good | C96: UNPACKED_GOOD | D96: Unpacked goods | E96: Indicator or description of whether delivered goods are transported unpackaged (e.g. as bulk goods or in tank trucks). Relevant for packaging classification, hazardous goods handling and sustainability reporting. | F96: VARCHAR2(16) | H96: False | I96: 4474503 | J96: NOT NULL, text/mixed, max length 8 | K96: bulk material; unpackaged goods; bulk shipment; unpacked material
A97: AR_KeyDate | B97: Unpacked good2 | C97: UNPACKED_GOOD2 | D97: Unpacked goods (TEXT) | F97: VARCHAR2(80) | H97: False | I97: DESMODUR VP.PU 1511 L | J97: NOT NULL, text/mixed, max length 40
A98: AR_KeyDate | B98: KPI AR-KeyDate: Amount in EUR | C98: KPI_AR_KEYDATE__AMOUNT_IN_EUR | D98: AR receivables amount in EUR at key date | E98: The open receivables amount in EUR at a defined key date. Part of the accounts receivable key date reporting. Used for WoC and receivables stock analyses. | F98: NUMBER(10,2) | H98: False | I98: 10510,44 | J98: NOT NULL, numeric, max prec/scale 10/2 | K98: receivables; accounts receivable; AR balance; outstanding receivables; open invoices
A99: AR_KeyDate | B99: KPI AR-KeyDate: Counter | C99: KPI_AR_KEYDATE__COUNTER | D99: Number of line items at key date | E99: Number of open customer line items (receivable positions) at the defined key date. Serves as the volume basis for average value calculations in AR key date reporting. | F99: NUMBER(10,3) | H99: False | I99: 0,999 | J99: NOT NULL, numeric, max prec/scale 10/3 | K99: receivable count; invoice count; open item count; line item count
A100: AR_KeyDate | B100: KPI AR-KeyDate: Net Value of Billing Item (DC) | C100: KPI_AR_KEYDATE__NET_VALUE_OF_BILLING_DC | D100: Net value of billing item in document currency at key date | E100: The net value of an invoice line item in document currency (DC) at the key date. Starting figure for the calculation of weighted receivables KPIs such as WoC and WAT. | F100: NUMBER(12,2) | H100: False | I100: 976068,6 | J100: NULL, numeric, max prec/scale 12/2 | K100: invoice value; billing value; receivable value; invoice amount
A101: AR_KeyDate | B101: KPI AR-KeyDate: Weighted WoC Target days | C101: KPI_AR_KEYDATE__WEIGHTED_WOC_TARGET_DAYS | D101: Weighted WoC target days at key date | E101: The weighted target days for Weeks of Credit (WoC) at the key date, calculated on the basis of agreed payment terms. Used as a benchmark figure against actual outstanding days. The actual Weighted WoC Target days is calculated by dividing Weighted WoC Target days by Amount in EUR for each data point. | F101: NUMBER(21,14) | H101: False | I101: 630626,66 | J101: NULL, numeric, max prec/scale 21/14 | K101: WOC target; weeks of credit target; target credit days
...

Sheet 4. Metrics
A1: METRICS
A2: One row per metric the AI can compute. Each metric maps to a SQL pattern the AI instantiates at query time. keywords drive metric selection; critical_notes prevent common mistakes.
A3: ℹ Instructions: Add one row per supported metric. metric_name must be unique and match exactly how it is referenced in the GT sheet. keywords = comma-separated phrases a user might say (the AI selects the metric by matching these). sql_example uses {placeholders} for dynamic values (time filter, dimension columns, etc.) that the AI fills in at runtime. critical_notes = hard rules the AI must follow when using this metric — most important column for accuracy.
A4: Covestro | C4: (Covestro) | E4: (Covestro) | N4: Core Filter bei Sales, Qunatity, Margin, aber nicht bei OTIF & Receivables
A5: metric_name | B5: category | C5: description | D5: when_to_use | E5: formula | F5: keywords | G5: sql_example | H5: relevant_tables | I5: output_columns | J5: critical_notes | K5: example_args
A6: Var. Product Costs per kg | B6: Sales | C6: Variable product costs incurred per kilogram sold. Measures production cost efficiency relative to volume. Lower values generally indicate better cost efficiency. | D6: Use when the question asks for analyzing production cost efficiency, cost developments, margin drivers, product profitability, or benchmarking costs across products and business units. | E6: (KPI COSMOS: Product Costs, Var.) / (KPI COSMOS: Gross Sales Qty (in+ex)) | F6: Var./kg, variable cost per kg; product cost per kg; manufacturing cost per kg; production cost efficiency; cost/kg; unit production cost; variable manufacturing cost per kg; variable product cost analysis; variable cost performance | G6: SELECT {dimension_columns}, ROUND( SUM(cos.KPI_COSMOS__PRODUCT_COSTS__VAR) / NULLIF(SUM(cos.KPI_COSMOS__GROSS_SALES_QTY__I), 0), 2 ) AS product_costs_var_per_qty FROM cos WHERE {current_time_filter} AND {core_business_indicator} {dimension_filter_clauses} {group_by_clause} {order_by_clause} {limit_clause}; | H6: COSMOS | I6: product_costs_var_per_qty | K6: {"metric_name":"Product Costs Var per Qty","time_period":{"FISCAL_YEAR_PERIOD":"2025"},"dimensions":["PRODUCED_MATERIAL"],"order_by":"product_costs_var_per_qty DESC","limit":10}
A7: OTIF Rate | B7: OTIF | C7: Percentage of deliveries that were completed On Time and In Full quantity (OTIF). Measures customer service performance and supply chain reliability. | D7: Use when evaluating delivery performance and fulfillment quality. | E7: (KPI OTIF: # OTIF) / (KPI OTIF: # total deliveries) *100 | F7: OTIF; on time and in full; delivery performance; delivery reliability; fulfillment rate; customer service KPI; logistics KPI; shipment performance, percentage of OTIF-compliant deliveries, OTIF compliance | G7: SELECT {dimension_columns}, ROUND( SUM(o.KPI_OTIF____OTIF) * 100.0 / NULLIF(SUM(o.KPI_OTIF____TOTAL_DELIVERIES), 0), 2 ) AS otif_rate FROM o WHERE {current_time_filter} {dimension_filter_clauses} {group_by_clause} {order_by_clause} {limit_clause}; | H7: OTIF | I7: otif_rate | K7: {"metric_name":"OTIF Rate","time_period":{"FISCAL_YEAR_PERIOD":"2025"},"dimensions":["Marketing Customer ship-to"],"order_by":"otif_rate DESC","limit":10}
A8: WAT Target | B8: Working capital | C8: The amount-weighted contractual payment term days (target days) of all open receivable positions at the key date | D8: Use when comparing the WAT compared to the target and when assessing receivables management, customer payment terms and working capital targets | E8: (KPI AR-KeyDate: Weighted target days) / (KPI AR-KeyDate: Amount in EUR) | F8: WAT target; targeted weighted average payment term; payment target days; receivables target; customer payment terms; AR target days; collection terms; working capital target | G8: SELECT {dimension_columns}, ROUND( SUM(kd.KPI_AR_KEYDATE__WEIGHTED_TARGET_DAYS) / NULLIF(SUM(kd.KPI_AR_KEYDATE__AMOUNT_IN_EUR), 0), 2 ) AS wat_target FROM kd WHERE {current_time_filter} {dimension_filter_clauses} {group_by_clause} {order_by_clause} {limit_clause}; | H8: AR-KeyDate | I8: wat_target | K8: {"metric_name":"WAT Target","time_period":{"FISCAL_YEAR_PERIOD":"2025"},"dimensions":["PRODUCED_MATERIAL"],"order_by":"wat_target DESC","limit":10}
A9: WOC Target | B9: Working capital | C9: The weighted target days for Weeks of Credit (WoC) at the key date. Used as a benchmark figure against actual outstanding days. | D9: Use when analyzing the weeks of credit target | E9: (KPI AR-KeyDate: Weighted WoC Target days) / (KPI AR-KeyDate: Amount in EUR) | F9: weeks of credit target | G9: SELECT {dimension_columns}, ROUND( SUM(kd.KPI_AR_KEYDATE__WEIGHTED_WOC_TARGET_DAYS) / NULLIF(SUM(kd.KPI_AR_KEYDATE__AMOUNT_IN_EUR), 0), 2 ) AS woc_target FROM kd WHERE {current_time_filter} {dimension_filter_clauses} {group_by_clause} {order_by_clause} {limit_clause}; | H9: AR-KeyDate | I9: woc_target | K9: {"metric_name":"WOC Target","time_period":{"FISCAL_YEAR_PERIOD":"2025"},"dimensions":["PRODUCED_MATERIAL"],"order_by":"woc_target DESC","limit":10}
A10: MI1 in % | B10: Sales | C10: Consolidated Marginal Income I as a percentage of Net Sales | D10: Use when analyzing profitability and margin performance | E10: (KPI COSMOS: Consolidated Marginal Income I) / (KPI COSMOS: Net Sales) * 100 | F10: MI1in % Sales; Margin I, %; marginal income 1 percentage; contribution margin percentage; gross margin percentage; profitability ratio; margin analysis | G10: SELECT {dimension_columns}, ROUND(100.0 * SUM(cos.KPI_COSMOS__CONSOLIDATED_MARGIN_I) / NULLIF(SUM(cos.KPI_COSMOS__NET_SALES), 0), 2) AS m1_in_prozent FROM cos WHERE {current_time_filter} AND {core_business_indicator} {dimension_filter_clauses} {group_by_clause} {order_by_clause} {limit_clause}; | H10: COSMOS | I10: m1_in_prozent | K10: {"metric_name":"MI1 in %","time_period":{"FISCAL_YEAR_PERIOD":"2025"},"dimensions":["PRODUCED_MATERIAL"],"order_by":"m1_in_prozent DESC","limit":10}
A11: Margin I per kg | B11: Sales | C11: Consolidated Marginal Income I generated per kilogram sold. Shows the contribution earned for each unit of sales volume. | D11: Use when evaluating profitability per volume unit | E11: (KPI COSMOS: Consolidated Marginal Income I) / (KPI COSMOS: Gross Sales Qty (in+ex)) | F11: MI1 per kg; margin per kg; contribution per kg; profitability per kg; earnings per kg; unit contribution margin | G11: SELECT {dimension_columns}, ROUND( SUM(cos.KPI_COSMOS__CONSOLIDATED_MARGIN_I) / NULLIF(SUM(cos.KPI_COSMOS__GROSS_SALES_QTY__IN_EX), 0), 2 ) AS margin_I_per_kg FROM cos WHERE {current_time_filter} AND {core_business_indicator} {dimension_filter_clauses} {group_by_clause} {order_by_clause} {limit_clause}; | H11: COSMOS | I11: margin_I_per_kg | K11: {"metric_name":"Margin I per kg","time_period":{"FISCAL_YEAR_PERIOD":"2025"},"dimensions":["PRODUCED_MATERIAL"],"order_by":"margin_I_per_kg DESC","limit":10}
A12: MI2a in % | B12: Sales | C12: Consolidated Marginal Income IIa as a percentage of Net Sales. Reflects profitability after additional costs beyond MI1 and provides a deeper profitability view | D12: Use when assessing operational profitability (as of Marginal Income 2a) in comparison to Net sales | E12: (KPI COSMOS: Consolidated Marginal Income IIa) / (KPI COSMOS: Net Sales) | F12: MI2a in % Sales; Margin IIa, %; marginal income 2a percentage; operating margin; profitability ratio; contribution margin 2a; net sales profitability | G12: SELECT {dimension_columns}, ROUND(100.0 * SUM(cos.KPI_COSMOS__CONSOLIDATED_MARGIN_IIa) / NULLIF(SUM(cos.KPI_COSMOS__NET_SALES), 0), 2) AS MI2a_in_prozent FROM cos WHERE {current_time_filter} AND {core_business_indicator} {dimension_filter_clauses} {group_by_clause} {order_by_clause} {limit_clause}; | H12: COSMOS | I12: MI2a_in_prozent | K12: {"metric_name":"MI2a in %","time_period":{"FISCAL_YEAR_PERIOD":"2025"},"dimensions":["PRODUCED_MATERIAL"],"order_by":"MI2a_in_prozent DESC","limit":10}
A13: MI2a per kg | B13: Sales | C13: Consolidated Marginal Income IIa generated per kilogram sold. Measures profitability per unit after accounting for additional cost elements included in MI2a. | D13: Use when comparing profitability (as of Marginal Income 2a) by volume | E13: (KPI COSMOS: Consolidated Marginal Income IIa) / (KPI COSMOS: Gross Sales Qty (in+ex)) | F13: Margin 2a per kg; operating profit per kg; profitability per kg; contribution per kg; margin/kg; earnings per unit | G13: SELECT {dimension_columns}, ROUND( SUM(cos.KPI_COSMOS__CONSOLIDATED_MARGIN_IIa) / NULLIF(SUM(cos.KPI_COSMOS__GROSS_SALES_QTY__IN_EX), 0), 2 ) AS MI2a_per_kg FROM cos WHERE {current_time_filter} AND {core_business_indicator} {dimension_filter_clauses} {group_by_clause} {order_by_clause} {limit_clause}; | H13: COSMOS | I13: MI2a_per_kg | K13: {"metric_name":"MI2a per kg","time_period":{"FISCAL_YEAR_PERIOD":"2025"},"dimensions":["PRODUCED_MATERIAL"],"order_by":"MI2a_per_kg DESC","limit":10}
A14: Overdue | B14: Working capital | C14: Total value of receivables that have passed their due date and remain unpaid. Indicates collection issues and potential credit risk exposure. | D14: Use when monitoring overdue accounts, credit risk, collection performance, or receivables aging. | E14: KPI AR-KeyDate: Amount in EUR with net_due_date <= Fiscal year/period | F14: overdue receivables; overdue AR; outstanding overdue invoices; late payments; past due amount; receivables aging; collections backlog, past due date | G14: SELECT {dimension_columns}, SUM(kd.KPI_AR_KEYDATE__AMOUNT_IN_EUR) AS overdue_receivables_eur FROM kd WHERE net_due_date <= FISCAL_YEAR_PERIOD {current_time_filter} {dimension_filter_clauses} {group_by_clause} {order_by_clause} {limit_clause}; | H14: AR-KeyDate | I14: overdue_receivables_eur | K14: {"metric_name":"Overdue","time_period":{"FISCAL_YEAR_PERIOD":"2025"},"dimensions":["PRODUCED_MATERIAL"],"order_by":"overdue_receivables_eur DESC","limit":10}
A15: Not yet due | B15: Working capital | C15: Value of receivables that are still within their agreed payment terms and have not yet reached their due date2 | D15: Use when assessing current receivables | E15: (KPI AR-KeyDate: Amount in EUR) - (Overdue) | F15: current receivables; receivables within terms; open receivables; outstanding not overdue; current AR; receivables aging | G15: SELECT {dimension_columns}, ROUND( SUM(kd.KPI_AR_KEYDATE__AMOUNT_IN_EUR) - SUM(kd.overdue_receivables_eur), 2 ) AS not_yet_due FROM kd WHERE {current_time_filter} AND {core_business_indicator} {dimension_filter_clauses} {group_by_clause} {order_by_clause} {limit_clause}; | H15: AR-KeyDate | I15: not_yet_due | K15: {"metric_name":"Not yet due","time_period":{"FISCAL_YEAR_PERIOD":"2025"},"dimensions":["PRODUCED_MATERIAL"],"order_by":"not_yet_due DESC","limit":10}
A16: % Overdue of Receivables | B16: Working capital | C16: Percentage of total receivables that are overdue. Measures the quality of accounts receivable and effectiveness of collection efforts | D16: Use when evaluating the current receivables and the corresponding overdues | E16: (Overdue) / (KPI AR-KeyDate: Amount in EUR) | F16: overdue percentage; overdue receivables ratio; AR overdue rate; collections performance; past due percentage | G16: SELECT {dimension_columns}, ROUND( 100.0 * SUM(kd.overdue_receivables_eur) / SUM(kd.KPI_AR_KEYDATE__AMOUNT_IN_EUR), 2 ) AS prozent_overdue_of_receivables FROM kd WHERE {current_time_filter} {dimension_filter_clauses} {group_by_clause} {order_by_clause} {limit_clause}; | H16: AR-KeyDate | I16: prozent_overdue_of_receivables | K16: {"metric_name":"% Overdue of Receivables","time_period":{"FISCAL_YEAR_PERIOD":"2025"},"dimensions":["PRODUCED_MATERIAL"],"order_by":"prozent_overdue_of_receivables DESC","limit":10}
A17: Volume Growth (%) | B17: Sales | C17: Percentage change in order volume compared with a prior period. Measures demand development | D17: Use when comparing order volume across two periods (e.g. June 2025 vs June 2026). Requires both time_period (current) and comparison_period (baseline). | E17: ((KPI Sales: Delivery Quantity KG_current -KPI Sales: Delivery Quantity KG_prior) / KPI Sales: Delivery Quantity KG_prior) * 100 | F17: order volume growth; sales volume growth; quantity growth; shipment growth; demand growth; volume trend; volume change; sales quantity increase; sales quantity decrease | G17: WITH totals AS ( SELECT {dimension_columns}, SUM(CASE WHEN s.ACT__GI_DAY BETWEEN TO_DATE('{current_start_date}') AND TO_DATE('{current_end_date}') THEN s.KPI_SALES__DELIVERY_QUANTITY_KG ELSE 0 END) AS current_total, SUM(CASE WHEN s.ACT__GI_DAY BETWEEN TO_DATE('{prior_start_date}') AND TO_DATE('{prior_end_date}') THEN s.KPI_SALES__DELIVERY_QUANTITY_KG ELSE 0 END) AS prior_total FROM s WHERE s.CORE_BUSINESS_INDICATOR IN ('C', 'P', 'T') AND (s.ACT__GI_DAY BETWEEN TO_DATE('{current_start_date}') AND TO_DATE('{current_end_date}') OR s.ACT__GI_DAY BETWEEN TO_DATE('{prior_start_date}') AND TO_DATE('{prior_end_date}')) {dimension_filter_clauses} {group_by_clause} ) SELECT {dimension_columns}, ROUND(current_total, 2) AS current_total, ROUND(prior_total, 2) AS prior_total, ROUND(current_total - prior_total, 2) AS absolute_change, ROUND(100.0 * (current_total - prior_total) / NULLIF(prior_total, 0), 2) AS volume_growth_prozent FROM totals {order_by_clause} {limit_clause}; | H17: Sales | I17: current_total, prior_total, absolute_change, volume_growth_prozent | K17: {"metric_name":"Volume Growth (%)","time_period":{"FISCAL_YEAR_PERIOD":"2025"},"dimensions":["PRODUCED_MATERIAL"],"order_by":"volume_growth_prozent DESC","limit":10}
A18: Net Sales Growth (%) | B18: Sales | C18: Percentage change in Net Sales between a current period and a comparable prior period (YoY, QoQ, MoM). Measures topline momentum. | D18: Use when comparing Net Sales across two periods (e.g. June 2025 vs June 2026). Requires both time_period (current) and comparison_period (baseline). | E18: ((COPA Net sales_current - COPA Net sales_prior) / COPA Net sales_prior) * 100 | F18: net sales growth; net sales change; growth in Net Sales; compare net sales; net sales YoY; net sales QoQ; net sales MoM; topline growth; net sales increase; net sales momentum; net sales trend; delta in net sales | G18: WITH totals AS ( SELECT {dimension_columns}, SUM(CASE WHEN cop.POSTING_DATE BETWEEN TO_DATE('{current_start_date}') AND TO_DATE('{current_end_date}') THEN cop.KPI_COPA__NET_SALES ELSE 0 END) AS current_total, SUM(CASE WHEN cop.POSTING_DATE BETWEEN TO_DATE('{prior_start_date}') AND TO_DATE('{prior_end_date}') THEN cop.KPI_COPA__NET_SALES ELSE 0 END) AS prior_total FROM cop WHERE cop.CORE_BUSINESS_INDICATOR IN ('C', 'P', 'T') AND (cop.POSTING_DATE BETWEEN TO_DATE('{current_start_date}') AND TO_DATE('{current_end_date}') OR cop.POSTING_DATE BETWEEN TO_DATE('{prior_start_date}') AND TO_DATE('{prior_end_date}')) {dimension_filter_clauses} {group_by_clause} ) SELECT {dimension_columns}, ROUND(current_total, 2) AS current_total, ROUND(prior_total, 2) AS prior_total, ROUND(current_total - prior_total, 2) AS absolute_change, ROUND(100.0 * (current_total - prior_total) / NULLIF(prior_total, 0), 2) AS metric_value FROM totals {order_by_clause} {limit_clause}; | H18: Sales | I18: current_total, comparison_total, absolute_change | J18: WITHIN-YEAR QoQ (same year, different quarters): Do NOT use this metric — it compares to prior year's same quarter. Use net sales with sequential_delta=true and quarter in dimensions instead. MULTI-YEAR TREND (3+ years): Use net sales with sequential_delta=true, not this metric. Always present all four output columns: current_total, comparison_total, absolute_change, metric_value (%). | K18: {"metric_name":"net sales Growth (%)","time_period":{"fiscal_year":"2024"},"comparison_period":{"fiscal_year":"2023"},"dimensions":["region_name"],"order_by":"absolute_change DESC"}
A19: Selling Price | B19: Sales | C19: Average net selling price per unit (kg) sold. Measures realized pricing and supports pricing strategy | D19: Use when analyzing pricing performance, price realization, price changes, product mix effects, and driver of net sales & order volume | E19: (KPI COPA: Net sales) / (KPI COPA: Gross Sales Qty) | F19: selling price; average selling price; ASP; price per kg; realized price; sales price; unit price; net price; pricing analysis; pricing KPI | G19: SELECT {dimension_columns}, ROUND( SUM(cop.KPI_COPA__NET_SALES) / NULLIF(SUM(cop.KPI_COPA__GROSS_SALES_QTY), 0), 2 ) AS selling_price FROM cop WHERE {current_time_filter} AND {core_business_indicator} {dimension_filter_clauses} {group_by_clause} {order_by_clause} {limit_clause}; | H19: COPA | I19: selling_price | K19: {"metric_name":"Selling Price","time_period":{"FISCAL_YEAR_PERIOD":"2025"},"dimensions":["PRODUCED_MATERIAL"],"order_by":"selling_price DESC","limit":10}
A20: Receivables | B20: Working capital | C20: =VLOOKUP(E20,'3. Column Info'!B6:E102,4,FALSE) -> The open receivables amount in EUR at a defined key date. Part of the accounts receivable key date reporting. Used for WoC and receivables stock analyses. | D20: Use when analyzing total accounts receivable exposure, outstanding customer balances, receivables stock, working capital tied up in customers, customer credit exposure, or regional/customer-level AR balances at a specific reporting date. Do not use for collection performance or payment behavior trends over time; use AR-PM metrics instead. | E20: KPI AR-KeyDate: Amount in EUR | F20: receivables; accounts receivable; AR balance; outstanding receivables; open invoices | G20: SELECT KPI_AR_KEYDATE__AMOUNT_IN_EUR FROM kd | H20: AR-KeyDate
A21: Line items | B21: Working capital | C21: =VLOOKUP(E21,'3. Column Info'!B7:E103,4,FALSE) -> Number of open customer line items (receivable positions) at the defined key date. Serves as the volume basis for average value calculations in AR key date reporting. | D21: Use when analyzing the number of open receivables, invoice volume, customer open-item exposure, receivables portfolio size, or as a denominator for weighted AR calculations. Do not use as a measure of monetary exposure. | E21: KPI AR-KeyDate: Counter | F21: receivable count; invoice count; open item count; line item count | G21: SELECT KPI_AR_KEYDATE__COUNTER FROM kd | H21: AR-KeyDate
A22: Net value of billing item | B22: Working capital | C22: =VLOOKUP(E22,'3. Column Info'!B8:E104,4,FALSE) -> The net value of an invoice line item in document currency (DC) at the key date. Starting figure for the calculation of weighted receivables KPIs such as WoC and WAT. | D22: Use when analyzing invoice-level receivables values, billing values in document currency, or when calculating weighted working-capital metrics such as WAT and WoC. Do not use for consolidated reporting in EUR. | E22: KPI AR-KeyDate: Net Value of Billing Item (DC) | F22: invoice value; billing value; receivable value; invoice amount | G22: SELECT KPI_AR_KEYDATE__NET_VALUE_OF_BILLING_ITEM FROM kd | H22: AR-KeyDate
A23: Weighted WoC target days | B23: Working capital | C23: =VLOOKUP(E23,'3. Column Info'!B9:E105,4,FALSE) -> The weighted target days for Weeks of Credit (WoC) at the key date, calculated on the basis of agreed payment terms. Used as a benchmark figure against actual outstanding days. The actual Weighted WoC Target days is calculated by dividing Weighted WoC Target days by Amount in EUR for each data point. | D23: Use when evaluating target payment terms, benchmark credit conditions, contractual customer payment agreements, or working-capital targets. Useful for comparing actual receivables performance against target conditions. | E23: KPI AR-KeyDate: Weighted WoC Target days | F23: WOC target; weeks of credit target; target credit days | G23: SELECT KPI_AR_KEYDATE__WEIGHTED_WOC_TARGET_DAYS FROM kd | H23: AR-KeyDate
A24: Weighted target days | B24: Working capital | C24: =VLOOKUP(E24,'3. Column Info'!B10:E106,4,FALSE) -> The amount-weighted contractual payment term days (target days) of all open receivable positions at the key date. Basis for the calculation of WAT (Weighted Average Terms). The actual weighted target days is calculated by dividing Weighted target days by Amount in EUR for each data point. | D24: Use when analyzing average contractual payment terms across a receivables portfolio, customer term structures, or WAT calculations. Do not use to assess actual payment behavior. | E24: KPI AR-KeyDate: Weighted target days | F24: WAT target; payment target days; target payment terms | G24: SELECT KPI_AR_KEYDATE__WEIGHTED_TARGET_DAYS FROM kd | H24: AR-KeyDate
A25: Receivables - PM | B25: Working capital | C25: =VLOOKUP(E25,Tabelle14[[column_name]:[description]],4,FALSE) -> The receivables amount in EUR within the AR Performance Monitoring (AR-PM). Period-related figure for evaluating receivables performance. | D25: Use when monitoring receivables performance over a reporting period, evaluating working-capital performance, or tracking AR trends over time. Do not use for balance-sheet snapshots at a specific key date. | E25: KPI AR-PM: Amount EUR | F25: receivables amount; AR amount; outstanding balance | G25: SELECT KPI_AR_PM__AMOUNT_EUR FROM pm | H25: AR-PM
A26: Line items - PM | B26: Working capital | C26: =VLOOKUP(E26,'3. Column Info'!B$197:E$604,4,FALSE) -> Number of customer line items in AR Performance Monitoring. Volume basis for weighted average KPIs in AR period reporting. | D26: Use when analyzing the volume of receivable positions in period-based AR performance reporting or when calculating weighted average AR indicators. Do not use for monetary analyses. | E26: KPI AR-PM: Counter | F26: item count; invoice count; receivable count | G26: SELECT KPI_AR_PM__COUNTER FROM pm | H26: AR-PM
A27: WoC deviation from target | B27: Working capital | C27: =VLOOKUP(E27,'3. Column Info'!B$197:E$604,4,FALSE) -> The difference between actual WoC (Weeks of Credit) and the target value. Positive value = payment term exceeded; negative value = payment term undercut. Operational control indicator for receivables management. | D27: Use when evaluating whether actual customer payment performance exceeds or misses working-capital targets. Useful for working-capital reviews, collection management, and AR performance monitoring. Positive values indicate deterioration versus target. | E27: KPI AR-PM: Diff WoC Target | F27: WOC deviation; variance to target WoC; credit term variance; week of credit deviation | G27: SELECT KPI_AR_PM__DIFF_WOC_TARGET FROM pm | H27: AR-PM
A28: Effective days outstanding | B28: Working capital | C28: =VLOOKUP(E28,'3. Column Info'!B$197:E$604,4,FALSE) -> EDO = WAT + WDD. Indicates the actual weighted outstanding days, i.e. the sum of the agreed payment terms (WAT) and the average delay (WDD). Corresponds to the operational DSO (Days Sales Outstanding). | D28: Use when measuring actual weighted customer payment duration, operational DSO performance, collection effectiveness, or customer payment behavior. Use as the primary KPI for outstanding receivables duration. | E28: KPI AR-PM: EDO (Effective Days Outstanding) | F28: EDO; days outstanding; operational DSO; collection days | G28: SELECT KPI_AR_PM__EDO__EFFECTIVE_DAYS_OUTSTANDING FROM pm | H28: AR-PM
A29: Performance days | B29: Working capital | C29: =VLOOKUP(E29,'3. Column Info'!B$197:E$604,4,FALSE) -> The total number of days a receivable was actually open, taking into account all influencing factors (WAT + WDD + Posting Days). Represents the total weighted duration from invoice creation through payment realization including administrative processing delays. Overall evaluation measure of AR performance. | D29: Use when assessing the full end-to-end receivables cycle from invoice creation to payment, including payment delays and internal processing delays. Useful for operational AR efficiency analysis. | E29: KPI AR-PM: Performance Days | F29: performance days; AR time performance; collection duration | G29: SELECT KPI_AR_PM__PERFORMANCE_DAYS FROM pm | H29: AR-PM
A30: Posting days | B30: Working capital | C30: =VLOOKUP(E30,'3. Column Info'!B$197:E$604,4,FALSE) -> The number of days between the invoice date and the actual posting date in the system. Provides insight into internal posting delays that affect AR performance. Reported separately to distinguish administrative delays from actual payment delays. | D30: Use when investigating internal administrative delays, delayed posting processes, or accounting process efficiency. Do not use to evaluate customer payment behavior. | E30: KPI AR-PM: Posting Days | F30: posting delay; processing days; posting duration | G30: SELECT KPI_AR_PM__POSTING_DAYS FROM pm | H30: AR-PM
A31: WAT Receivables | B31: Working capital | C31: =VLOOKUP(E31,'3. Column Info'!B$197:E$604,4,FALSE) -> WAT = Weighted Average Terms. Indicates the amount-weighted contractual payment term days of all open receivables in a period. Example: WAT of 86.4 days means that payment terms of 86.4 days were agreed on average. A strategic KPI in Working Capital Management. | D31: Use when analyzing contractual payment terms, customer credit conditions, payment-term negotiations, or strategic working-capital management. | E31: KPI AR-PM: WAT Receivables | F31: WAT; weighted average terms; payment terms; average payment period | G31: SELECT KPI_AR_PM__WAT_RECEIVABLES FROM pm | H31: AR-PM
A32: Weighted delay days | B32: Working capital | C32: =VLOOKUP(E32,'3. Column Info'!B$197:E$604,4,FALSE) -> WDD = Weighted Delay Days. Indicates the amount-weighted average days of delay beyond the agreed payment term. A WDD of 5.2 days means that customers pay on average 5.2 days after the due date. An operational KPI in the Working Capital Framework. Formula: EDO − WAT = WDD. | D32: Use when evaluating how late customers pay relative to agreed payment terms. Useful for collection effectiveness reviews, overdue payment analyses, and customer payment discipline assessments. | E32: KPI AR-PM: WDD (Weighted Delay Days) | F32: WDD; payment delay; overdue days; collection delay | G32: SELECT KPI_AR_PM__WDD__WEIGHTED_DELAY_DAYS FROM pm | H32: AR-PM
A33: Gross sales quantity (CO-PA) | B33: Sales | C33: =VLOOKUP(E33,'3. Column Info'!B$197:E$604,4,FALSE) -> The total invoiced quantity (in KG) before deduction of credit memos and returns, as recorded in SAP Profitability Analysis (CO-PA). Starting figure of the CO-PA revenue calculation. | D33: Use when analyzing invoiced sales volume, sales quantities, volume growth, product demand, customer volume, or pricing calculations. | E33: KPI COPA: Gross Sales Qty | F33: gross sales volume; quantity sold; sales volume COPA; shipped volume; kilograms sold COPA; invoiced quantity | G33: SELECT KPI_COPA__GROSS_SALES_QTY FROM cop | H33: COPA
A34: Gross sales (CO-PA) | B34: Sales | C34: =VLOOKUP(E34,'3. Column Info'!B$197:E$604,4,FALSE) -> The total invoiced revenue (gross revenues) before deduction of discounts, bonuses and other revenue deductions, recorded in CO-PA. Starting point of the revenue calculation in the contribution margin scheme. | D34: Use when analyzing total invoiced revenue before discounts, rebates, bonuses, and deductions. Useful for topline sales analysis and revenue bridge calculations. | E34: KPI COPA: Gross sales | F34: gross sales; gross revenue; invoiced revenue; topline before deductions | G34: SELECT KPI_COPA__GROSS_SALES FROM cop | H34: COPA
A35: Net proceeds (CO-PA) | B35: Sales | C35: =VLOOKUP(E35,'3. Column Info'!B$197:E$604,4,FALSE) -> Net Sales less sales adjustments, represents revenue after application of sales deductions and sales adjustments within CO-PA reporting. | D35: Use when analyzing realized revenue after sales deductions and adjustments. Suitable for commercial performance reporting and revenue quality analyses. | E35: KPI COPA: Net proceeds | F35: net proceeds; proceeds; realized revenue | G35: SELECT KPI_COPA__NET_PROCEEDS FROM cop | H35: COPA
A36: Net sales (CO-PA) | B36: Sales | C36: =VLOOKUP(E36,'3. Column Info'!B$197:E$604,4,FALSE) -> Gross Sales less sales deductions. | D36: Use when analyzing net commercial revenue, revenue growth, sales performance, and selling-price calculations. | E36: KPI COPA: Net sales | F36: revenue; net revenue; sales; turnover | G36: SELECT KPI_COPA__NET_SALES FROM cop | H36: COPA
A37: Sales adjustments (CO-PA) | B37: Sales | C37: =VLOOKUP(E37,'3. Column Info'!B$197:E$604,4,FALSE) -> Correction postings to revenue in CO-PA, e.g. quantity corrections, price corrections of retrospectively posted conditions or periodic revaluations. Reported between Net Proceeds and Net Sales. | D37: Use when investigating revenue corrections, pricing changes, retrospective settlements, quantity corrections, or commercial accounting adjustments. | E37: KPI COPA: Sales adjustments | F37: revenue adjustments; sales corrections; price adjustments | G37: SELECT KPI_COPA__SALES_ADJUSTMENTS FROM cop | H37: COPA
... A68: Net value of delivery | B68: Sales | C68: =VLOOKUP(E68,'3. Column Info'!B$197:E$604,4,FALSE) -> The net value of a delivery line item in EUR, converted from the document currency at the applicable posting exchange rate. Standard reporting currency for all cross-dimensional revenue and margin KPIs in reporting. Aggregatable across all dimensions (customer, product, region, period). | D68: Use when analyzing shipment revenue, order fulfillment value, customer delivery value, or revenue by product, customer, region, and period in EUR. Preferred delivery-value KPI for cross-country reporting. | E68: KPI Sales: Net value delivery EUR | F68: delivery value EUR; shipment revenue EUR; delivered sales value | G68: SELECT KPI_SALES__NET_VALUE_DELIVERY_EUR FROM s | H68: Sales
A70: 🟡 Yellow rows = example metrics from product reference model. SQL uses {placeholders} resolved at runtime. Replace with your client's metric definitions before use.

Sheet 5. GT — Ask Zora
A1: GROUND TRUTH — ASK ZORA
A2: One row per question-answer pair. These are the verified examples the AI uses to validate its behaviour. The more complete and accurate these rows are, the better the AI performs.
A3: ℹ Instructions: One row per Q&A pair. sample_question = exact user phrasing to test. calculation_logic = step-by-step plain English (the AI reads this to understand HOW to answer). sql_query = verified SQL that produces the correct result against your data. expected_answer = the verified correct output (numbers + narrative). comments = edge cases, known issues, or logic notes for the team.
A4: id | B4: category | C4: sample_question | D4: source_tables | E4: calculation_logic | F4: metric_used | G4: sql_query | H4: expected_answer | I4: comments
A5: 1 | B5: Sales | C5: What was the total net sales for Q2 2025? | D5: copa | E5: 1) Filter copa table where core_business_indicator = 'C', 'P' or 'T' and calendar_day is in Q2 2025 (Apr 1 - Jun 30, calendar quarter assumed). 2) SUM(Net Sales). | F5: Net sales (CO-PA) | G5: SELECT ROUND(SUM(c.net_sales), 2) AS net_sales FROM copa c WHERE c.core_business_indicator IN ('C', 'P', 'T') AND c.posting_date BETWEEN '2025-04-01' AND '2025-06-30'; | H5: Pending | I5: April to June is considered as Q2
A6: 2 | B6: Sales | C6: Show me revenue by region for full year 2025, sorted highest to lowest | D6: copa | E6: 1) Filter copa table where core_business_indicator = core_business_indicator = 'C', 'P' or 'T' and calendar_day is in FY2025. 2) Group by Region ship-to. 3) SUM(Net Sales) per region. 4) Sort descending. | F6: Net sales (CO-PA) | G6: SELECT c.region_ship_to, ROUND(SUM(c.net_sales), 2) AS net_sales FROM copa c WHERE c.core_business_indicator IN ('C', 'P', 'T') AND c.posting_date BETWEEN '2025-01-01' AND '2025-12-31' GROUP BY c.region_ship_to ORDER BY net_sales DESC; | H6: Pending | I6: "Region" defaulted to Region ship-to (delivery region). If it is ambigiguos, then Agent should ask or give all possible answers
A7: 3 | B7: Sales | C7: Show me delta from month Jan 2025 to March 2026 on Marketing level 3 | D7: copa | E7: 1) Compute Net Sales per Marketing Level 3 for Jan 2025. 2) Compute Net Sales per Marketing Level 3 for Mar 2026. 3) Subtract period A from period B per Marketing Level 3 value (full outer join to catch categories present in only one period). | F7: Net sales (CO-PA) | G7: WITH period_a AS ( SELECT c.marketing_level_3, SUM(c.net_sales) AS net_sales FROM copa c WHERE c.core_business_indicator IN ('C', 'P', 'T') AND c.posting_date BETWEEN '2025-01-01' AND '2025-01-31' GROUP BY c.marketing_level_3 ), period_b AS ( SELECT c.marketing_level_3, SUM(c.net_sales) AS net_sales FROM copa c WHERE c.core_business_indicator IN ('C', 'P', 'T') AND c.posting_date BETWEEN '2026-03-01' AND '2026-03-31' GROUP BY c.marketing_level_3 ) SELECT COALESCE(a.marketing_level_3, b.marketing_level_3) AS marketing_level_3, ROUND(COALESCE(b.net_sales,0) - COALESCE(a.net_sales,0), 2) AS net_sales_delta FROM period_a a FULL OUTER JOIN period_b b ON a.marketing_level_3 = b.marketing_level_3 ORDER BY net_sales_delta DESC; | H7: Pending | I7: Metric not stated in the question — assumed Copa Net Sales. "Month" interpreted as the full calendar month.
A8: 4 | B8: Margin | C8: How did our marginal income change from Q1 2026 to Q2 2026? | D8: cosmos | E8: 1) Compute Consolidated Marginal Income I for Q1 2026 (Jan-Mar). 2) Compute for Q2 2026 (Apr-Jun). 3) Report absolute and % delta. | F8: Consolidated marginal income I | G8: WITH q1 AS ( SELECT SUM(cm.consolidated_marginal_income_i) AS cmi1 FROM cosmos cm WHERE cm.core_business_indicator IN ('C', 'P', 'T') AND cm.calendar_day BETWEEN '2026-01-01' AND '2026-03-31' ), q2 AS ( SELECT SUM(cm.consolidated_marginal_income_i) AS cmi1 FROM cosmos cm WHERE cm.core_business_indicator IN ('C', 'P', 'T') AND cm.calendar_day BETWEEN '2026-04-01' AND '2026-06-30' ) SELECT ROUND(q2.cmi1 - q1.cmi1, 2) AS cmi1_delta, ROUND(100.0 * (q2.cmi1 - q1.cmi1) / NULLIF(q1.cmi1, 0), 1) AS cmi1_delta_pct FROM q1, q2; | H8: Pending | I8: "Marginal income" defaulted to CMI I (not CMI IIa) since unspecified. Uses the stored Consolidated Marginal Income I column directly rather than recomputing from Gross Sales/Deductions/Adjustments/Product Costs
A9: 5 | B9: Margin | C9: What are the top 3 of less performing product in PH3 in reference to marginal income 1? | D9: cosmos | E9: 1) SUM(CMI I) per Material within the given PH3 category. 2) Rank ascending. 3) Return bottom 3. | F9: Consolidated marginal income I | G9: SELECT cm.material, ROUND(SUM(cm.consolidated_marginal_income_i), 2) AS cmi1 FROM cosmos cm WHERE cm.core_business_indicator IN ('C', 'P', 'T') AND cm.prod_hier_3 = '{ph3_value}' GROUP BY cm.material ORDER BY cmi1 ASC LIMIT 3; | H9: Pending | I9: Less performing" interpreted as lowest total CMI I (absolute EUR), not lowest CMI I per kg or lowest margin %
A10: 6 | B10: Order | C10: How did order volume grow from HY2025 to HY2026? | D10: sales | E10: 1) SUM(Delivery Quantity KG) for HY2025 (Jan-Jun 2025). 2) Same for HY2026 (Jan-Jun 2026). 3) % change. | F10: Volume Growth (%) | G10: WITH hy2025 AS ( SELECT SUM(s.delivery_quantity_kg) AS volume FROM sales s WHERE s.core_business_indicator IN ('C', 'P', 'T') AND s.act_gi_day BETWEEN '2025-01-01' AND '2025-06-30' ), hy2026 AS ( SELECT SUM(s.delivery_quantity_kg) AS volume FROM sales s WHERE s.core_business_indicator IN ('C', 'P', 'T') AND s.act_gi_day BETWEEN '2026-01-01' AND '2026-06-30' ) SELECT ROUND(100.0 * (hy2026.volume - hy2025.volume) / NULLIF(hy2025.volume, 0), 1) AS volume_growth_pct FROM hy2025, hy2026; | H10: Pending | I10: "Order volume" measures delivered shipment volume
A11: 7 | B11: Order | C11: What is the average order volume size in FY2025, by BE? | D11: sales | E11: 1) SUM(Delivery Quantity KG) per SBE for FY2025. 2) COUNT(*) rows per SBE (proxy for number of deliveries). 3) Divide. | F11: Order Volume | G11: SELECT s.sbe, ROUND(SUM(s.delivery_quantity_kg) / NULLIF(COUNT(*), 0), 1) AS avg_delivery_volume_kg FROM sales s WHERE s.core_business_indicator IN ('C', 'P', 'T') AND s.act_gi_day BETWEEN '2025-01-01' AND '2025-12-31' GROUP BY s.sbe;
A12: 8 | B12: WAT | C12: What percentage of our Account Receivables is overdue as of end of 2025? | D12: kd | E12: 1) Take the AR-KeyDate snapshot at/nearest 2025-12-31 (it is a snapshot table). 2) SUM(Amount in EUR) WHERE Net due date < 2025-12-31 = overdue. 3) SUM(Amount in EUR) total for that snapshot. 4) Divide, x100. | F12: % Overdue of Receivables | G12: WITH snapshot AS ( SELECT MAX(posting_date) AS snap_date FROM ar_keydate WHERE posting_date <= '2025-12-31' ) SELECT ROUND(100.0 * SUM(CASE WHEN kd.net_due_date < '2025-12-31' THEN kd.amount_in_eur ELSE 0 END) / NULLIF(SUM(kd.amount_in_eur), 0), 1) AS pct_overdue FROM ar_keydate kd, snapshot WHERE kd.posting_date = snapshot.snap_date; | H12: Pending
A13: 9 | B13: OTIF | C13: What's our OTIF rate by carrier over the last quarter, and which failure reason is driving the misses? | D13: otif | E13: 1) OTIF Rate per Carrier for the last quarter. 2) Breakdown of failure-reason counts (# late GI, # late create, # late transport, # not in full) per carrier, to identify the dominant driver. | F13: OTIF Rate | G13: SELECT o.carrier, ROUND(100.0 * SUM(o.otif_count) / NULLIF(SUM(o.total_deliveries), 0), 1) AS otif_rate, SUM(o.late_gi) AS late_goods_issue, SUM(o.late_create) AS late_order_creation, SUM(o.late_transport) AS late_transport, SUM(o.not_in_full) AS not_in_full FROM otif o WHERE o.act_gi_day BETWEEN {quarter_start} AND {quarter_end} GROUP BY o.carrier ORDER BY otif_rate ASC; | H13: Pending
A14: 10 | B14: Margin | C14: Which products have the widest gap between MI1% and MI2a%, and is that gap driven by fixed cost? | D14: cosmos | E14: 1) MI1% and MI2a% per Material. 2) Gap = MI1% - MI2a%. 3) Rank descending by gap (widest gap = most fixed-cost burden relative to variable margin). | F14: MI1 in %, MI2a in % | G14: SELECT cm.material, ROUND(100.0 * SUM(cm.consolidated_marginal_income_i) / NULLIF(SUM(cm.net_sales), 0), 1) AS mi1_pct, ROUND(100.0 * SUM(cm.consolidated_marginal_income_ii_a) / NULLIF(SUM(cm.net_sales), 0), 1) AS mi2a_pct, ROUND(100.0 * (SUM(cm.consolidated_marginal_income_i) - SUM(cm.consolidated_marginal_income_ii_a)) / NULLIF(SUM(cm.net_sales), 0), 1) AS gap_pp FROM cosmos cm GROUP BY cm.material ORDER BY gap_pp DESC LIMIT 10; 12 answerable prompts (ids 1,2,3,4,5,6,8,9,10,11,12,13) + 1 documented rejection (id 7, with a working replacement at id 11). ids 1-4 rewritten from the original draft to fix the master_sales_table/core_business_indicator/CMI-I-sign-error bugs already caught in KPI Cards. Every SQL query deliberately omits core_business_indicator pending the client discussion, per the same decision made for KPI Cards and Daily News Logic. | H14: Pending
A15: 11 | B15: Order | C15: How is the order volume pipeline for customer xy for the next 3 months?
A16: 12 | B16: WAT | C16: Show me the WAT of ship to customer xy and show the deviation to target | F16: WAT Receivables, Target WAT
A19: 🟡 Yellow rows = example Q&A pairs. Replace expected_answer with values from YOUR data. Verify every SQL query against your actual database before deploying.

Sheet 6. KPI Cards
A1: KPI CARDS
A2: One row per KPI card widget. KPI cards display a single headline metric with a comparison badge. They run SQL directly — no AI generation. The SQL must return exactly one row.
A3: ℹ Instructions: main_value_sql returns the primary number shown on the card (one row, one column: metric_value). comparison_sql returns the badge value (e.g. MoM change) — also one row. favorable_direction: 'higher' if a bigger number is good (e.g. revenue), 'lower' if a smaller number is good (e.g. DSO, overdue %). target_value is the goal shown in the footnote. Leave blank if no target is defined.
B4: Covestro | C4: Covestro | E4: Covestro | H4: Covestro
A5: card_id | B5: card_title | C5: main_value_description | D5: main_value_sql | E5: comparison_label | F5: comparison_sql | G5: footnote | H5: target_value | I5: favorable_direction | J5: source_tables | K5: notes
A6: kpi_net_sales_mtd | B6: Net Sales | C6: Total Net Sales for the current month, in € millions | D6: SELECT ROUND(SUM(c.KPI_COPA__NET_SALES) / 1000000.0, 2) AS metric_value FROM cop c WHERE c.core_business_indicator IN ('C', 'P', 'T') AND c.POSTING_DATE >= DATE_TRUNC('month', CURRENT_DATE) AND c.POSTING_DATE <= CURRENT_DATE; | E6: vs. prior year (same month), % | F6: WITH curr AS ( SELECT SUM(c.KPI_COPA__NET_SALES) AS net_sales FROM cop c WHERE c.core_business_indicator IN ('C', 'P', 'T') AND c.POSTING_DATE >= DATE_TRUNC('month', CURRENT_DATE) AND c.POSTING_DATE <= CURRENT_DATE ), prior AS ( SELECT SUM(c.KPI_COPA__NET_SALES) AS net_sales FROM cop c WHERE c.core_business_indicator IN ('C', 'P', 'T') AND c.POSTING_DATE >= DATEADD(year, -1, DATE_TRUNC('month', CURRENT_DATE)) AND c.POSTING_DATE <= DATEADD(year, -1, CURRENT_DATE) ) SELECT ROUND(100.0 * (curr.net_sales - prior.net_sales) / NULLIF(prior.net_sales, 0), 1) AS metric_value FROM curr, prior; | G6: vs prior year | I6: higher | J6: cop | K6: Single-table query against copa, alias cop. Uses the column KPI_COPA__NET_SALES directly (= Gross Sales - Sales Deductions).
A7: kpi_cmi1_ytd | B7: Marginal Income 1 | C7: Consolidated Marginal Income I, year-to-date, in € millions | D7: SELECT ROUND(SUM(cm.KPI_COSMOS__CONSOLIDATED_MARGIN_I) / 1000000.0, 2) AS metric_value FROM cos cm WHERE cm.core_business_indicator IN ('C', 'P', 'T') AND cm.CALENDAR_DAY >= DATE_TRUNC('year', CURRENT_DATE) AND cm.CALENDAR_DAY <= CURRENT_DATE; | E7: vs. prior year, % | F7: WITH curr AS ( SELECT SUM(cm.KPI_COSMOS__CONSOLIDATED_MARGIN_I) AS cmi1 FROM cos cm WHERE cm.core_business_indicator IN ('C', 'P', 'T') AND cm.CALENDAR_DAY >= DATE_TRUNC('year', CURRENT_DATE) AND cm.CALENDAR_DAY <= CURRENT_DATE ), prior AS ( SELECT SUM(cm.KPI_COSMOS__CONSOLIDATED_MARGIN_I) AS cmi1 FROM cos cm WHERE c.core_business_indicator IN ('C', 'P', 'T') AND cm.CALENDAR_DAY >= DATEADD(year, -1, DATE_TRUNC('year', CURRENT_DATE)) AND cm.CALENDAR_DAY <= DATEADD(year, -1, CURRENT_DATE) ) SELECT ROUND(100.0 * (curr.cmi1 - prior.cmi1) / NULLIF(prior.cmi1, 0), 1) AS metric_value FROM curr, prior; | G7: vs prior year | I7: higher | J7: cos | K7: Single-table query against cosmos, alias cos. Uses the column KPI_COSMOS__CONSOLIDATED_MARGIN_I column directly (validated = Net Proceeds - Product Costs Var).
A8: kpi_volume_mtd | B8: Order Volume | C8: Total delivered volume for the current month, in kg | D8: SELECT ROUND(SUM(s.KPI_SALES__DELIVERY_QUANTITY_KG), 0) AS metric_value FROM sales s WHERE s.core_business_indicator IN ('C', 'P', 'T') AND s.ACT__GI_DAY >= DATE_TRUNC('month', CURRENT_DATE) AND s.ACT__GI_DAY <= CURRENT_DATE; | E8: vs. prior month, % | F8: WITH curr AS ( SELECT SUM(s.KPI_SALES__DELIVERY_QUANTITY_KG) AS volume FROM sales s WHERE s.core_business_indicator IN ('C', 'P', 'T') AND s.ACT__GI_DAY >= DATE_TRUNC('month', CURRENT_DATE) AND s.ACT__GI_DAY <= CURRENT_DATE ), prior AS ( SELECT SUM(s.KPI_SALES__DELIVERY_QUANTITY_KG) AS volume FROM sales s WHERE s.core_business_indicator IN ('C', 'P', 'T') AND s.ACT__GI_DAY >= DATEADD(month, -1, DATE_TRUNC('month', CURRENT_DATE)) AND s.ACT__GI_DAY <= DATEADD(month, -1, CURRENT_DATE) ) SELECT ROUND(100.0 * (curr.volume - prior.volume) / NULLIF(prior.volume, 0), 1) AS metric_value FROM curr, prior; | G8: vs prior month | I8: higher | J8: Sales | K8: Single-table query against sales. Uses the column KPI_SALES__DELIVERY_QUANTITY_KG directly and filtered on ACT__GI_DAY.
A9: kpi_wat_mtd | B9: Weighted average term | C9: Amount-weighted average payment term (WAT) across open receivables for the current month, in days | D9: SELECT ROUND(SUM(pm.KPI_AR_PM__WAT_RECEIVABLES * pm.KPI_AR_PM__AMOUNT_EUR) / NULLIF(SUM(pm.KPI_AR_PM__AMOUNT_EUR), 0), 1) AS metric_value FROM pm WHERE pm.core_business_indicator IN ('C', 'P', 'T') AND pm.POSTING_DATE >= DATE_TRUNC('month', CURRENT_DATE) AND pm.POSTING_DATE<= CURRENT_DATE; | E9: vs. target, days | F9: WITH actual AS ( SELECT SUM(pm.KPI_AR_PM__WAT_RECEIVABLES* pm.KPI_AR_PM__AMOUNT_EUR) / NULLIF(SUM(pm.KPI_AR_PM__AMOUNT_EUR), 0) AS wat FROM pm WHERE pm.core_business_indicator IN ('C', 'P', 'T') AND pm.posting_date >= DATE_TRUNC('month', CURRENT_DATE) AND pm.posting_date <= CURRENT_DATE ), target AS ( SELECT SUM(kd.KPI_AR_KEYDATE__WEIGHTED_TARGET_DAYS) / NULLIF(SUM(kd.KPI_AR_KEYDATE__AMOUNT_IN_EUR), 0) AS target_days FROM kd WHERE kd.core_business_indicator IN ('C', 'P', 'T') AND kd.posting_date = ( SELECT MAX(posting_date) FROM kd WHERE posting_date <= CURRENT_DATE ) ) SELECT ROUND(actual.wat - target.target_days, 1) AS metric_value FROM actual, target; | G9: vs target | I9: lower | J9: AR-PM, AR-KeyDate | K9: Two independent tables, no row-level join — AR-PM (transactional, per posting/due-date) is aggregated on its own for the actual value; AR-KeyDate (a month-end snapshot) is aggregated separately for the target. WAT_receivables needs to be checked if we are directly receiving from the real data KPI, or should we use the formula. Also, the values from 2 tables needs to be verified.
A10: kpi_otif_mtd | B10: OTIF % | C10: Percentage of deliveries completed on time and in full for the current month | D10: SELECT ROUND(100.0 * SUM(o.KPI_OTIF____OTIF) / NULLIF(SUM(o.KPI_OTIF____TOTAL_DELIVERIES), 0), 1) AS metric_value FROM otif o WHERE o.core_business_indicator IN ('C', 'P', 'T') AND o.ACT__GI_DAY>= DATE_TRUNC('month', CURRENT_DATE) AND o.ACT__GI_DAY<= CURRENT_DATE; | E10: vs. prior month, pp | F10: WITH curr AS ( SELECT 100.0 * SUM(o.KPI_OTIF____OTIF) / NULLIF(SUM(o.KPI_OTIF____TOTAL_DELIVERIES), 0) AS pct FROM otif o WHERE o.core_business_indicator IN ('C', 'P', 'T') AND o.ACT__GI_DAY>= DATE_TRUNC('month', CURRENT_DATE) AND o.ACT__GI_DAY <= CURRENT_DATE ), prior AS ( SELECT 100.0 * SUM(o.KPI_OTIF____OTIF) / NULLIF(SUM(o.KPI_OTIF____TOTAL_DELIVERIES), 0) AS pct FROM otif o WHERE o.core_business_indicator IN ('C', 'P', 'T') AND o.ACT__GI_DAY>= DATEADD(month, -1, DATE_TRUNC('month', CURRENT_DATE)) AND o.ACT__GI_DAY<= DATEADD(month, -1, CURRENT_DATE) ) SELECT ROUND(curr.pct - prior.pct, 1) AS metric_value FROM curr, prior; | G10: vs prior month | I10: higher | J10: OTIF | K10: Single-table query against otif. KPI_OTIF____OTIF and KPI_OTIF____TOTAL_DELIVERIES are confirmed used for calculation.
A11: kpi_cmi1_pct_ytd | B11: MI1 in % | C11: Consolidated Marginal Income I as a percentage of Net Sales, year-to-date | D11: SELECT ROUND(100.0 * SUM(cm.KPI_COSMOS__CONSOLIDATED_MARGIN_I) / NULLIF(SUM(cm.KPI_COSMOS__NET_SALES), 0), 1) AS metric_value FROM cos cm WHERE cm.core_business_indicator IN ('C', 'P', 'T') AND cm.calendar_day >= DATE_TRUNC('year', CURRENT_DATE) AND cm.calendar_day <= CURRENT_DATE; | E11: vs. prior year, pp | F11: WITH curr AS ( SELECT 100.0 * SUM(cm.KPI_COSMOS__CONSOLIDATED_MARGIN_I) / NULLIF(SUM(cm.KPI_COSMOS__NET_SALES), 0) AS pct FROM cos cm WHERE cm.core_business_indicator IN ('C', 'P', 'T') AND cm.calendar_day >= DATE_TRUNC('year', CURRENT_DATE) AND cm.calendar_day <= CURRENT_DATE ), prior AS ( SELECT 100.0 * SUM(cm.KPI_COSMOS__CONSOLIDATED_MARGIN_I) / NULLIF(SUM(cm.KPI_COSMOS__NET_SALES), 0) AS pct FROM cos cm WHERE cm.core_business_indicator IN ('C', 'P', 'T') AND cm.calendar_day >= DATEADD(year, -1, DATE_TRUNC('year', CURRENT_DATE)) AND cm.calendar_day <= DATEADD(year, -1, CURRENT_DATE) ) SELECT ROUND(curr.pct - prior.pct, 1) AS metric_value FROM curr, prior; | G11: vs prior year | I11: higher | J11: cos | K11: Single-table query against cosmos. Denominator is the stored KPI_COSMOS__NET_SALES column (Gross Sales - Sales Deductions).
A13: 🟡 Yellow rows = example KPI card definitions. {placeholders} are resolved at runtime. Verify each SQL returns exactly ONE row before deploying.
A15: clarifications
A16: Technical name have been used for column names
A17: Table name or Alias have been used
A18: How should the date be filtered, currently uses current date, but if the data is old then it has to be fixed
A19: Core Business Indicator have been used now for all KPIs

Sheet 7. Performance Pulse
A1: PERFORMANCE PULSE
A2: One row per Performance Pulse widget. Each widget runs SQL, then the AI generates a structured response (chart + table + narrative) according to the output_format template. Different from KPI cards — these produce generated language.
A3: ℹ Instructions: sql_query produces the raw data. ground_truth = verified numbers the AI response must match. output_format = the exact structure the AI must follow (chart type, table columns, narrative shape). sample_prompt = the user question that triggers this widget. testing_notes = known issues or edge cases.
B4: Covestro | C4: Covestro | D4: Covestro | I4: Covestro
A5: pp_id | B5: pp_grouping | C5: pp_title | D5: what_it_shows | E5: source_tables | F5: calculation_logic | G5: sql_query | H5: ground_truth | I5: output_format | J5: sample_prompt | K5: testing_notes
A6: PP-01 | B6: Financial Performance – Seller View | C6: Financial Performance per Customer – MM YYYY YTD | D6: Net Sales, Order volume, Marginal Income 1 and Marginal Income 2a (incl. Marginal Income 1 and Marginal Income 2a in relation to Net Sales and Order Volume) per top 50 customer - ranked by Volume (incl. totals) in YTD view, enabling fiancial overview of the performance of the top 50 customers | E6: COSMOS | F6: 1) Filter COSMOS to the configured current fiscal YTD (January through the current reporting cutoff) and apply the approved core-business filter. 2) Group by Sold-to booked customer. 3) Sum COSMOS Net Sales, Gross Sales Quantity (in+ex) as Order Volume, Consolidated Marginal Income I, and Consolidated Marginal Income IIa. 4) Calculate MI1 % = MI1 / Net Sales × 100, MI1 per kg = MI1 / Order Volume, and MI2a % = MI2a / Net Sales × 100; return blank where the denominator is zero. 5) Rank customers by Order Volume descending and keep the top 50. 6) Add a total row by summing the top-50 base amounts and recalculating each ratio from those totals; do not average customer percentages. | G6: WITH customer_ytd AS ( SELECT COALESCE(SOLD_TO2, TO_VARCHAR(SOLD_TO), 'Unknown') AS customer, SUM(KPI_COSMOS__GROSS_SALES_QTY__IN_EX) AS volume_kg, SUM(KPI_COSMOS__NET_SALES) AS net_sales_eur, SUM(KPI_COSMOS__CONSOLIDATED_MARGIN_I) AS mi1_eur, SUM(KPI_COSMOS__CONSOLIDATED_MARGIN_IIa) AS mi2a_eur FROM cos WHERE CORE_BUSINESS_INDICATOR IN ('C', 'P', 'T') AND CALENDAR_DAY BETWEEN DATE_TRUNC('year', TO_DATE('{reporting_date}')) AND TO_DATE('{reporting_date}') GROUP BY SOLD_TO, SOLD_TO2 ), top_50 AS ( SELECT *, ROW_NUMBER() OVER (ORDER BY volume_kg DESC, customer) AS rank_no FROM customer_ytd QUALIFY rank_no <= 50 ), results AS ( SELECT rank_no AS sort_order, customer, volume_kg, net_sales_eur, mi1_eur, 100 * mi1_eur / NULLIF(net_sales_eur, 0) AS mi1_pct, mi1_eur / NULLIF(volume_kg, 0) AS mi1_eur_per_kg, mi2a_eur, 100 * mi2a_eur / NULLIF(net_sales_eur, 0) AS mi2a_pct FROM top_50 UNION ALL SELECT 999999, 'TOTAL TOP 50', SUM(volume_kg), SUM(net_sales_eur), SUM(mi1_eur), 100 * SUM(mi1_eur) / NULLIF(SUM(net_sales_eur), 0), SUM(mi1_eur) / NULLIF(SUM(volume_kg), 0), SUM(mi2a_eur), 100 * SUM(mi2a_eur) / NULLIF(SUM(net_sales_eur), 0) FROM top_50 ) SELECT customer AS sold_to_booked, ROUND(volume_kg, 0) AS volume_kg, ROUND(net_sales_eur, 2) AS net_sales_eur, ROUND(mi1_eur, 2) AS marginal_income_1_eur, ROUND(mi1_pct, 1) AS mi1_pct, ROUND(mi1_eur_per_kg, 2) AS mi1_eur_per_kg, ROUND(mi2a_eur, 2) AS marginal_income_2a_eur, ROUND(mi2a_pct, 1) AS mi2a_pct FROM results ORDER BY sort_order; | I6: Table: Sold to booked | Volume | Net Sales | Marginal Income 1 | MI1 in % | MI1 per kg | Marginal Income 2a | MI2a in % Narrative: 1 opening sentence (total attainment). Then 3–4 bullets covering top performer and any notable pattern | J6: Show me the YTD financial performance of our top 50 customers | K6: user selects reporting date.
A7: PP-01 | B7: Financial Performance – Seller View | C7: Operational View | D7: Net Sales, Order volume, Marginal Income 1 and Marginal Income 2a (incl. Marginal Income 1 and Marginal Income 2a in relation to Net Sales) for the current YTD and the YTD a year ago, enabling absolute and relative deviation analysis of the financial performance | E7: COSMOS | F7: 1) Define current YTD as January through the configured reporting cutoff and prior YTD as the same dates one year earlier. 2) Filter COSMOS to each period using the approved core-business filter. 3) For each period, sum Net Sales, Gross Sales Quantity (in+ex) as Order Volume, Consolidated Marginal Income I, and Consolidated Marginal Income IIa. 4) Calculate MI1 % = MI1 / Net Sales × 100 and MI2a % = MI2a / Net Sales × 100; return blank where Net Sales is zero. 5) Create one row per KPI and unit. 6) Calculate D abs = current YTD − prior YTD and D % = D abs / prior YTD × 100; for percentage KPIs, show the absolute change in percentage points and the relative change in D %. | G7: WITH totals AS ( SELECT SUM(CASE WHEN CALENDAR_DAY >= DATE_TRUNC('year', TO_DATE('{reporting_date}')) THEN KPI_COSMOS__NET_SALES ELSE 0 END) AS curr_sales, SUM(CASE WHEN CALENDAR_DAY < DATE_TRUNC('year', TO_DATE('{reporting_date}')) THEN KPI_COSMOS__NET_SALES ELSE 0 END) AS prev_sales, SUM(CASE WHEN CALENDAR_DAY >= DATE_TRUNC('year', TO_DATE('{reporting_date}')) THEN KPI_COSMOS__GROSS_SALES_QTY__IN_EX ELSE 0 END) AS curr_volume, SUM(CASE WHEN CALENDAR_DAY < DATE_TRUNC('year', TO_DATE('{reporting_date}')) THEN KPI_COSMOS__GROSS_SALES_QTY__IN_EX ELSE 0 END) AS prev_volume, SUM(CASE WHEN CALENDAR_DAY >= DATE_TRUNC('year', TO_DATE('{reporting_date}')) THEN KPI_COSMOS__CONSOLIDATED_MARGIN_I ELSE 0 END) AS curr_mi1, SUM(CASE WHEN CALENDAR_DAY < DATE_TRUNC('year', TO_DATE('{reporting_date}')) THEN KPI_COSMOS__CONSOLIDATED_MARGIN_I ELSE 0 END) AS prev_mi1, SUM(CASE WHEN CALENDAR_DAY >= DATE_TRUNC('year', TO_DATE('{reporting_date}')) THEN KPI_COSMOS__CONSOLIDATED_MARGIN_IIa ELSE 0 END) AS curr_mi2a, SUM(CASE WHEN CALENDAR_DAY < DATE_TRUNC('year', TO_DATE('{reporting_date}')) THEN KPI_COSMOS__CONSOLIDATED_MARGIN_IIa ELSE 0 END) AS prev_mi2a FROM cos WHERE CORE_BUSINESS_INDICATOR IN ('C', 'P', 'T') AND CALENDAR_DAY BETWEEN DATEADD(year, -1, DATE_TRUNC('year', TO_DATE('{reporting_date}'))) AND TO_DATE('{reporting_date}') ), kpis AS ( SELECT 1 AS sort_no, 'Net Sales' AS kpi, 'EUR' AS unit, prev_sales AS prior_ytd, curr_sales AS current_ytd FROM totals UNION ALL SELECT 2, 'Order Volume', 'kg', prev_volume, curr_volume FROM totals UNION ALL SELECT 3, 'Marginal Income 1', 'EUR', prev_mi1, curr_mi1 FROM totals UNION ALL SELECT 4, 'MI1 in %', '%', 100*prev_mi1/NULLIF(prev_sales,0), 100*curr_mi1/NULLIF(curr_sales,0) FROM totals UNION ALL SELECT 5, 'Marginal Income 2a', 'EUR', prev_mi2a, curr_mi2a FROM totals UNION ALL SELECT 6, 'MI2a in %', '%', 100*prev_mi2a/NULLIF(prev_sales,0), 100*curr_mi2a/NULLIF(curr_sales,0) FROM totals ) SELECT kpi AS "KPIs", unit AS "unit", ROUND(prior_ytd, 2) AS prior_ytd, ROUND(current_ytd, 2) AS current_ytd, ROUND(current_ytd - prior_ytd, 2) AS d_abs, ROUND(100 * (current_ytd - prior_ytd) / NULLIF(prior_ytd, 0), 1) AS d_pct FROM kpis ORDER BY sort_no; | I7: Table: "KPIs" | "unit" | MM YYYY -1 | MM YYYY | D abs | D % Narrative: 1 opening sentence. Then 3–4 bullets covering over time development and notable pattern | J7: Summarize the total financial performance and show the development over time by comparing the current YTD with the previous year
A8: PP-01 | B8: Financial Performance – Seller View | C8: Margins: LTM | D8: Development of the Order Volumes, Marginal Income 1 per kg and Marginal Income 2a per kg over the last 12 months | E8: COSMOS | F8: 1) Select the 12 consecutive reporting months ending with the configured current reporting month. 2) Filter COSMOS to those months using the approved core-business filter. 3) Group by calendar month and sum Gross Sales Quantity (in+ex) as Order Volume, Consolidated Marginal Income I, and Consolidated Marginal Income IIa. 4) Calculate MI1 per kg = monthly MI1 / monthly Order Volume and MI2a per kg = monthly MI2a / monthly Order Volume; return blank where volume is zero. 5) Sort the 12 months chronologically. 6) Plot monthly Order Volume as bars and MI1 per kg and MI2a per kg as lines. | G8: SELECT DATE_TRUNC('month', CALENDAR_DAY) AS reporting_month, ROUND(SUM(KPI_COSMOS__GROSS_SALES_QTY__IN_EX), 0) AS order_volume_kg, ROUND(SUM(KPI_COSMOS__CONSOLIDATED_MARGIN_I) / NULLIF(SUM(KPI_COSMOS__GROSS_SALES_QTY__IN_EX), 0), 2) AS mi1_eur_per_kg, ROUND(SUM(KPI_COSMOS__CONSOLIDATED_MARGIN_IIa) / NULLIF(SUM(KPI_COSMOS__GROSS_SALES_QTY__IN_EX), 0), 2) AS mi2a_eur_per_kg FROM cos WHERE CORE_BUSINESS_INDICATOR IN ('C', 'P', 'T') AND CALENDAR_DAY BETWEEN DATEADD(month, -11, DATE_TRUNC('month', TO_DATE('{reporting_date}'))) AND TO_DATE('{reporting_date}') GROUP BY reporting_month ORDER BY reporting_month; | I8: Chart: bar chart for the order volumes, MI1 per kg and MI2a per kg as lines Narrative: 1 opening sentence. Then 3–4 bullets covering over time development and notable pattern | J8: Show the last twelve month development of the order volume and the marginal incomes related to volume
A9: PP-02 | B9: Cash Performance | C9: CM – Payment History Overview – Standard KPIs | D9: WAT, WDD and EDO over time, showing the payment history y | E9: AR-PM | F9: 1) Filter AR-PM to the requested trend period; 2) Group records by reporting month. 3) Sum Amount EUR for the monthly weight base. 4) Calculate amount-weighted WAT = SUM(WAT Receivables × Amount EUR) / SUM(Amount EUR) and amount-weighted WDD = SUM(WDD × Amount EUR) / SUM(Amount EUR). 5) Calculate amount-weighted EDO, use EDO = WAT + WDD. 6) Do not take a simple average of row-level KPI values. 7) Sort months chronologically and plot WAT, WDD, and EDO as three lines. | G9: SELECT DATE_TRUNC('month', POSTING_DATE) AS reporting_month, ROUND(SUM(KPI_AR_PM__WAT_RECEIVABLES * KPI_AR_PM__AMOUNT_EUR) / NULLIF(SUM(KPI_AR_PM__AMOUNT_EUR), 0), 1) AS wat_receivables_days, ROUND(SUM(KPI_AR_PM__WDD__WEIGHTED_DELAY_DAYS * KPI_AR_PM__AMOUNT_EUR) / NULLIF(SUM(KPI_AR_PM__AMOUNT_EUR), 0), 1) AS wdd_days, ROUND(SUM(KPI_AR_PM__EDO__EFFECTIVE_DAYS_OUTSTANDING * KPI_AR_PM__AMOUNT_EUR) / NULLIF(SUM(KPI_AR_PM__AMOUNT_EUR), 0), 1) AS edo_days FROM pm WHERE POSTING_DATE BETWEEN DATEADD(month, -11, DATE_TRUNC('month', TO_DATE('{reporting_date}'))) AND TO_DATE('{reporting_date}') GROUP BY reporting_month ORDER BY reporting_month; | I9: Chart: Line chart - WAT Receivables, WDD, EDO Narrative: 1 opening sentence. Then 3–4 bullets covering over time development and notable pattern | J9: How did the payment terms develop over time?
A10: PP-02 | B10: Cash Performance | C10: CM – Overdue Receivables- Receivables/Overdue | D10: Analysis of Receivables: overdue vs. not yet due (incl. Relation of overdue receivables to total receivables) | E10: AR-KeyDate | F10: 1) Treat AR-KeyDate as a month-end snapshot table: for each reporting month, select the latest available key date in that month. 2) At each selected key date, calculate total Receivables = SUM(Amount in EUR). 3) Calculate Overdue Receivables = SUM(Amount in EUR) for open items whose Net Due Date is on or before the key date. 4) Calculate Not Yet Due = Total Receivables − Overdue Receivables. 5) Calculate Overdue % = Overdue Receivables / Total Receivables × 100; return blank where total receivables is zero. 6) Sort snapshots chronologically and plot Overdue and Not Yet Due as stacked bars with Overdue % as a line. | G10: WITH snapshots AS ( SELECT DATE_TRUNC('month', POSTING_DATE) AS reporting_month, MAX(POSTING_DATE) AS snapshot_date FROM kd WHERE POSTING_DATE BETWEEN DATEADD(month, -11, DATE_TRUNC('month', TO_DATE('{reporting_date}'))) AND TO_DATE('{reporting_date}') GROUP BY reporting_month ), monthly AS ( SELECT s.reporting_month, s.snapshot_date, SUM(k.KPI_AR_KEYDATE__AMOUNT_IN_EUR) AS receivables_eur, SUM(CASE WHEN k.NET_DUE_DATE <= s.snapshot_date THEN k.KPI_AR_KEYDATE__AMOUNT_IN_EUR ELSE 0 END) AS overdue_eur FROM snapshots s JOIN kd k ON k.POSTING_DATE = s.snapshot_date GROUP BY s.reporting_month, s.snapshot_date ) SELECT reporting_month, snapshot_date, ROUND(overdue_eur, 2) AS overdue_eur, ROUND(receivables_eur - overdue_eur, 2) AS not_yet_due_eur, ROUND(100 * overdue_eur / NULLIF(receivables_eur, 0), 1) AS overdue_pct FROM monthly ORDER BY reporting_month; | I10: Chart: stacked bar chart for the overdue & not yet due (receivables), overdue % as line Narrative: 1 opening sentence. Then 3–4 bullets covering over time development and notable pattern | J10: Show me the portion of overdue / not yet due receivables over time
A11: PP-02 | B11: Cash Performance | C11: CM – Overdue Receivables Worklist – Overdue (DL >0) | D11: Receivables (incl. Overdue) per top 50 Customer (ranked by Overdue) for the current YTD and for the previous year | E11: AR-KeyDate | F11: 1) Because AR-KeyDate is a snapshot, select one current snapshot at the latest available key date in the configured reporting month and one comparison snapshot for the equivalent month/date one year earlier; do not sum snapshots across YTD. 2) For each snapshot, group by Sold-to party and sum total Receivables (Amount in EUR). 3) Sum Overdue for items with delay days > 0, also Net Due Date before the snapshot date. 4) Calculate current Overdue % = current Overdue / current Receivables × 100; return blank where receivables is zero. 5) Combine the two customer aggregates after aggregation using the customer key so customers present in only one year are retained; do not join raw snapshot rows. 6) Rank by current Overdue descending, keep the top 50, and return current Overdue, current Receivables, current Overdue %, prior-year Overdue, and prior-year Receivables. | G11: WITH dates AS ( SELECT TO_DATE('{reporting_date}') AS current_date, DATEADD(year, -1, TO_DATE('{reporting_date}')) AS prior_date ), snapshots AS ( SELECT MAX(CASE WHEN POSTING_DATE BETWEEN DATE_TRUNC('month', d.current_date) AND d.current_date THEN POSTING_DATE END) AS current_snapshot, MAX(CASE WHEN POSTING_DATE BETWEEN DATE_TRUNC('month', d.prior_date) AND d.prior_date THEN POSTING_DATE END) AS prior_snapshot FROM kd CROSS JOIN dates d ), customer_ar AS ( SELECT k.SOLD_TO, COALESCE(k.SOLD_TO2, TO_VARCHAR(k.SOLD_TO), 'Unknown') AS customer, SUM(CASE WHEN k.POSTING_DATE = s.current_snapshot THEN k.KPI_AR_KEYDATE__AMOUNT_IN_EUR ELSE 0 END) AS current_receivables, SUM(CASE WHEN k.POSTING_DATE = s.current_snapshot AND k.NET_DUE_DATE <= s.current_snapshot THEN k.KPI_AR_KEYDATE__AMOUNT_IN_EUR ELSE 0 END) AS current_overdue, SUM(CASE WHEN k.POSTING_DATE = s.prior_snapshot THEN k.KPI_AR_KEYDATE__AMOUNT_IN_EUR ELSE 0 END) AS prior_receivables, SUM(CASE WHEN k.POSTING_DATE = s.prior_snapshot AND k.NET_DUE_DATE <= s.prior_snapshot THEN k.KPI_AR_KEYDATE__AMOUNT_IN_EUR ELSE 0 END) AS prior_overdue FROM kd k CROSS JOIN snapshots s WHERE k.POSTING_DATE IN (s.current_snapshot, s.prior_snapshot) GROUP BY k.SOLD_TO, k.SOLD_TO2 ) SELECT customer AS sold_to_party, ROUND(current_overdue, 2) AS overdue_current_eur, ROUND(current_receivables, 2) AS receivables_current_eur, ROUND(100 * current_overdue / NULLIF(current_receivables, 0), 1) AS overdue_pct_current, ROUND(prior_overdue, 2) AS overdue_prior_year_eur, ROUND(prior_receivables, 2) AS receivables_prior_year_eur FROM customer_ar QUALIFY ROW_NUMBER() OVER (ORDER BY current_overdue DESC, SOLD_TO) <= 50 ORDER BY current_overdue DESC, SOLD_TO; | I11: Table: Sold to party | Overdue MM YYYY | Receivables MM YYYY | % Overdue of Receivables | Overdue MM YYYY-1 | Receivables MM YYYY-1 Narrative: 1 opening sentence. Then 3–4 bullets covering top performer and any notable pattern | J11: Show me the overdue receivables of our top 50 customers for this year and compared to the year before
A13: 🟡 Yellow rows = example Performance Pulse definitions. ground_truth values must be verified against your actual data. output_format is the exact template the AI follows.

Sheet 8. Daily News Logic
A1: DAILY NEWS LOGIC
A2: One row per Daily News item. Each news item is automatically generated daily by the AI using the SQL query, formatted according to the headline and body templates, and verified against the ground truth numbers.
A3: ℹ Instructions: Daily News items are auto-generated narrative summaries — different from Performance Pulse (which the user triggers on demand). headline_template uses placeholders like [QTD], [+$Y], [Country A]. ground_truth = verified numbers from your data that the AI must match. chart_spec = the mini chart shown alongside the news item (type, axes, values). status: PASS = verified correct, FAIL = needs fix, PENDING = not yet tested.
B4: Covestro
A5: news_id | B5: news_item_title | C5: what_it_shows | D5: why_it_adds_value | E5: source_tables | F5: headline_template | G5: body_format | H5: calculation_logic | I5: ground_truth | J5: sql_query | K5: chart_spec | L5: status | M5: notes
A6: DN-01 | B6: Net Sales Surprises vs 7-Day Average | C6: The regions (ship-to) whose daily Net Sales deviated most from their own trailing 7-day average yesterday, split into biggest positive and biggest negative surprises, ranked by € impact. | D6: Surfaces fresh day-to-day momentum shifts and regional anomalies that a monthly or quarterly view would smooth over and hide. | E6: copa | F6: [Region A] +$[X] vs 7-day avg; [Region B] -$[Y] vs 7-day avg. | G6: Sentence 1 (today vs 7-day avg): "Today's Net Sales per region: [Region A] posted upside with +$[X] vs its 7-day average (+[Pct_A]%), while [Region B] came in -$[Y] below average (-[Pct_B]%)." Sentence 2 (summary): "Net daily surprise across all regions: +$[Net] ([N_above] regions above average, [N_below] below)." | H6: 1) Today's Net Sales per Region ship-to: SUM(net_sales) FROM copa WHERE posting_date = {as_of_date}, GROUP BY region_ship_to. 2) Trailing 7-day average per region: AVG of the 7 daily SUM(net_sales) totals for the 7 calendar days immediately before {as_of_date} (excludes {as_of_date} itself). 3) Filter to core business only: core_business_indicator IN ('C','P','T') — client-confirmed values for COPA. 4) Deviation € = today's value − 7-day average. Deviation % = Deviation € / 7-day average × 100. 5) Rank regions by deviation € descending; report top 2 positive and top 2 negative. | I6: TBD — cannot be derived from the sample data provided. Sample KPI values are randomly obfuscated per row. | J6: WITH daily_by_region AS ( SELECT c.region_ship_to, c.posting_date, SUM(c.net_sales) AS net_sales FROM copa c WHERE c.core_business_indicator IN ('C','P','T') AND c.posting_date BETWEEN DATEADD(day, -8, {as_of_date}) AND {as_of_date} GROUP BY c.region_ship_to, c.posting_date ), today AS ( SELECT region_ship_to, net_sales AS today_sales FROM daily_by_region WHERE posting_date = {as_of_date} ), trailing_avg AS ( SELECT region_ship_to, AVG(net_sales) AS avg_7day FROM daily_by_region WHERE posting_date < {as_of_date} GROUP BY region_ship_to ) SELECT t.region_ship_to, ROUND(t.today_sales, 0) AS today_sales, ROUND(a.avg_7day, 0) AS avg_7day, ROUND(t.today_sales - a.avg_7day, 0) AS deviation_eur, ROUND(100.0 * (t.today_sales - a.avg_7day) / NULLIF(a.avg_7day, 0), 1) AS deviation_pct FROM today t JOIN trailing_avg a ON t.region_ship_to = a.region_ship_to ORDER BY deviation_eur DESC; | K6: Two-bar chart per highlighted region: today's Net Sales vs 7-day average. X-axis: region name. Y-axis: Net Sales (€). Green bar = positive deviation, red = negative. One bar per region = the deviation (today - 7-day average , in Eur), extending up from zero baseline for positive surprises and down for negative ones. | L6: PENDING | M6: sql filter is based on {as_of_date}. This needs to be filled in as per real data
A7: DN-02 | B7: Product Mix Shifting by Customer | C7: The 5 customers whose share of revenue from low-margin products has moved most vs. the same quarter last year (QTD). | D7: Flags customers whose purchasing mix is quietly eroding — or improving — profitability, well before it would show up in a quarterly margin review. | E7: cosmos | F7: [Customer A]'s low-margin product share [+/-][X]pp YoY (QTD); [Customer B] [+/-][Y]pp. | G7: Sentence 1: "Over this quarter to date, [Customer A]'s share of revenue from low-margin products moved to [X]% from [X_PY]% a year ago ([+/-][Delta]pp)." Sentence 2 (summary): "Top 5 customers by product mix shift: [list]." | H7: 1) Filter to core business only: core_business_indicator IN ('C','P','T') — client-confirmed values. 2) For each Sold-to, flag each Prod.Hier.4 as low-margin if its CMI I margin % < 30%. 3) QTD this year: low-margin revenue share = SUM(Net Sales on low-margin products) / SUM(Net Sales, all products), per Sold-to. 4) Same computation for the same QTD window, prior year. 5) Deviation (pp) = this-year share − prior-year share. 6) Rank Sold-to by |deviation| descending; report top 5. | J7: WITH margin_flagged AS ( SELECT cm.sold_to, cm.prod_hier_4, cm.calendar_day, cm.net_sales, CASE WHEN (cm.consolidated_marginal_income_i / NULLIF(cm.net_sales,0)) < 0.30 THEN 1 ELSE 0 END AS is_low_margin FROM cosmos cm WHERE cm.core_business_indicator IN ('C','P','T') AND cm.calendar_day BETWEEN {qtd_start} AND {as_of_date} ), curr AS ( SELECT sold_to, SUM(CASE WHEN is_low_margin=1 THEN net_sales ELSE 0 END) AS low_margin_sales, SUM(net_sales) AS total_sales FROM margin_flagged GROUP BY sold_to ), prior AS ( SELECT cm.sold_to, SUM(CASE WHEN (cm.consolidated_marginal_income_i / NULLIF(cm.net_sales,0)) < 0.30 THEN cm.net_sales ELSE 0 END) AS low_margin_sales, SUM(cm.net_sales) AS total_sales FROM cosmos cm WHERE cm.core_business_indicator IN ('C','P','T') AND cm.calendar_day BETWEEN DATEADD(year,-1,{qtd_start}) AND DATEADD(year,-1,{as_of_date}) GROUP BY cm.sold_to ) SELECT c.sold_to, ROUND(100.0*c.low_margin_sales/NULLIF(c.total_sales,0),1) AS curr_share_pct, ROUND(100.0*p.low_margin_sales/NULLIF(p.total_sales,0),1) AS prior_share_pct, ROUND(100.0*c.low_margin_sales/NULLIF(c.total_sales,0) - 100.0*p.low_margin_sales/NULLIF(p.total_sales,0),1) AS deviation_pp FROM curr c JOIN prior p ON c.sold_to = p.sold_to ORDER BY ABS(deviation_pp) DESC LIMIT 5; | K7: Small multiples: one small bar pair per customer — low-margin revenue share this QTD vs same QTD last year. X-axis: customer name. Y-axis: % of revenue. One bar chart per customer. Bar = the percentage point change in low-amrgin share this QTD vs same QTD last year. | L7: PENDING | M7: Low margin threshold needs to be defined. qtr_start and as_of_date needs to be set.
A8: DN-03 | B8: Order Volume Pacing vs Previous Year | C8: The business entities (SBE) whose QTD ordered volume has deviated most, in %, from the same QTD period last year; top 2 positive and top 1 negative contributing SBEs. | D8: Gives an early, sub-quarterly read on which business lines are outpacing or lagging their own prior-year trajectory. | E8: sales | F8: [BE A] volume [+/-][X]% QTD vs PY; [BE B] [+/-][Y]%. | G8: Sentence 1: "QTD order volume: [BE A] is running [+/-][X]% vs prior year ([X_kg]kg vs [PY_kg]kg)." Sentence 2 (summary): "Top movers by volume: [list]." | H8: 1) Filter to core business only: core_business_indicator IN ('C','P','T') — client-confirmed values, matches your example syntax. 2) QTD delivered volume by SBE: SUM(delivery_quantity_kg) FROM sales WHERE core_business_indicator IN ('C','P','T') AND act_gi_day BETWEEN {qtd_start} AND {as_of_date}, GROUP BY sbe. 3) Same window, prior year: same computation shifted back exactly one year, same core-business filter applied. 4) Deviation kg = actual − prior year; Deviation % = Deviation kg / prior year × 100. 5) Rank SBE by |deviation %| descending. | I8: TBD — cannot be derived from the sample data provided. Sample KPI values are randomly obfuscated per row (per the merge log). | J8: WITH curr AS ( SELECT s.sbe, SUM(s.delivery_quantity_kg) AS qtd_volume FROM sales s WHERE s.core_business_indicator IN ('C','P','T') AND s.act_gi_day BETWEEN {qtd_start} AND {as_of_date} GROUP BY s.sbe ), prior AS ( SELECT s.sbe, SUM(s.delivery_quantity_kg) AS qtd_volume_py FROM sales s WHERE s.core_business_indicator IN ('C','P','T') AND s.act_gi_day BETWEEN DATEADD(year,-1,{qtd_start}) AND DATEADD(year,-1,{as_of_date}) GROUP BY s.sbe ) SELECT c.sbe, ROUND(c.qtd_volume,0) AS qtd_volume, ROUND(p.qtd_volume_py,0) AS qtd_volume_py, ROUND(c.qtd_volume - p.qtd_volume_py,0) AS deviation_kg, ROUND(100.0*(c.qtd_volume - p.qtd_volume_py)/NULLIF(p.qtd_volume_py,0),1) AS deviation_pct FROM curr c JOIN prior p ON c.sbe = p.sbe ORDER BY ABS(deviation_pct) DESC; | K8: Two-bar chart per SBE: current QTD volume vs prior-year QTD volume. X-axis: SBE name. Y-axis: Volume (kg). | L8: PENDING | M8: sql filter is based on {as_of_date}. This needs to be filled in as per real data
A14: 🟡 Yellow rows = example Daily News items. ground_truth must be verified against your data. status: PASS = tested and correct | FAIL = SQL or logic needs fixing | PENDING = not yet tested.

Sheet 9. Fiscal & Rounding Rules
A1: FISCAL & ROUNDING RULES
A2: Client-specific configuration the AI uses for time period logic, number formatting, and rounding. Must be completed before testing — incorrect fiscal config causes wrong period filters.
A3: ℹ Instructions: Fill in every row with your client's actual values. The AI reads this sheet to resolve 'current month', 'YTD', 'fiscal quarter' and format all numbers in responses consistently.
A4: Configuration Item | B4: Value
A5: FISCAL CALENDAR
A6: Fiscal Year Start Month | B6: January | F6: ← Enter the calendar month the fiscal year begins (e.g. January, April, October)
A7: Fiscal Year Label Convention | B7: YYYY (e.g. 2026) | F7: ← How the fiscal year is labelled — same as calendar year, or offset? (e.g. FY2024, 2024, FY24)
A8: Fiscal Quarter Q1 Months | B8: January, February, March | F8: ← List the 3 calendar months in fiscal Q1
A9: Fiscal Quarter Q2 Months | B9: April, May, June | F9: ← List the 3 calendar months in fiscal Q2
A10: Fiscal Quarter Q3 Months | B10: July, August, September | F10: ← List the 3 calendar months in fiscal Q3
A11: Fiscal Quarter Q4 Months | B11: October, November, December | F11: ← List the 3 calendar months in fiscal Q4
A12: Number of Fiscal Periods per Year | B12: 12 (monthly) | F12: ← 12 for monthly, 13 for 4-4-5 or 13-period calendars
A13: Current Fiscal Year | B13: 2026 | F13: ← The fiscal year to use as default when user does not specify a year
A14: Current Fiscal Month (number) | B14: 6 | F14: ← The fiscal month to use as default for MTD queries (1=first month of fiscal year)
A16: CURRENCY & REPORTING
A17: Primary Reporting Currency | B17: EUR | F17: ← The default currency for all AI responses and metric calculations
A18: Currency Symbol | B18: € | F18: ← Symbol prepended to monetary values in responses
A19: Currency Display Scale | B19: k€, m€, bn€ | F19: ← How amounts are displayed: Thousands ($K), Millions ($M), or Billions ($B)
A20: Multi-Currency Support | B20: no | F20: ← List any secondary currencies present in the data
A22: NUMBER FORMATTING & ROUNDING
A23: Revenue Rounding | B23: Overall 3 digits e.g. €412m or €41.2m --> 3 digits | F23: ← How revenue figures are rounded and displayed
A24: Percentage Rounding | B24: Overall 3 digits e.g. 42.3% --> 3 digits | F24: ← How percentages are displayed
A25: DSO / Days Rounding | B25: Overall 3 digits e.g. 48.1 days --> 3 digits | F25: ← How day-based metrics are rounded
A26: Deal Value Rounding | B26: - | F26: ← How individual deal values are displayed
A27: Volume / Quantity Rounding | B27: Overall 3 digits e.g. 1.12kg --> 3 digits | F27: ← How count/volume metrics are rounded
A28: Variance Display Convention | B28: see KPI cards | F28: ← E.g. revenue variance: +$3.4M = favorable. DSO variance: +5 days = unfavorable (label accordingly).
A30: SPECIAL BUSINESS RULES
A31: Budget Version Used | B31: no budget | F31: ← Which budget version to use: Original Budget, Revised Budget, Latest Forecast, etc.
A32: Forecast / Flash Version | B32: no forecast | F32: ← Which forecast version is the current flash/forecast baseline
A33: 'Favorable' Revenue Direction | B33: current month higher than previous period | F33: ← Define what favorable means for primary revenue metrics
A34: DSO Target | B34: no DSO | F34: ← Target DSO for badge coloring and footnote display
A35: Win Rate Target | B35: no win rate | F35: ← Target win rate for badge coloring and footnote display
A36: Overdue AR Target | B36: no target | F36: ← Threshold above which overdue % is flagged as elevated

Sheet 10. Requirements & Notes
A1: REQUIREMENTS & NOTES
A2: Free-form section for master prompt context, open questions, known data issues, and client-specific instructions that don't fit elsewhere. The AI may reference these when generating responses.
A3: ℹ Instructions: Use this sheet to capture anything not covered by the structured sheets. Sections below are suggested — add or remove rows freely. Master Prompt Context is particularly important: it tells the AI who it is, what it knows, and how to behave.
A4: Category | B4: Content / Notes
A5: MASTER PROMPT CONTEXT (System Instructions for AI)
A6: Role & Identity | B6: You are a digital FP&A co-worker supporting financial and sales performance analysis. Your role is to structure data, quantify drivers, and highlight patterns to assist human decision-making. You do not make business decisions — you surface the data to support them - from a financial and business driven / key account management perspective.
A7: Data Scope | B7: You have access to sales data, volume data, AR, working capital data like WAT and OTIF for FY2025 and FY2026 (HY1). Data covers four regions: [CLIENT TO FILL: e.g. North America, Europe/Middle East/Africa, Asia Pacific, Latin America]. The reporting currency is EUR. All monetary amounts are in EUR unless otherwise specified.
A8: Tone & Format | B8: Responses should be concise, numeric, and executive-ready. Always lead with the headline number. Use bullet points for drivers. Flag if data is unavailable rather than guessing. Positive revenue variance = Favorable. Negative = Unfavorable. Label explicitly.
A9: Hard Constraints | B9: 1. Never invent numbers — if data is missing say so. 2. Always filter is_active = TRUE unless the user asks for historical records. 3. For period-over-period questions always show both periods and the delta. 4. entity_segment = industry vertical. entity_category = business-size tier. Do not confuse them. 5. If question is unclear or metric /dimension selection is not clear, say so or provide proposals for multiple dimensions / metrics
A11: KNOWN DATA ISSUES & LIMITATIONS
A12: Issue: Budget Data | B12: no budget
A13: Issue: DSO Calculation | B13: no DSO
A14: [CLIENT TO COMPLETE] | B14: Add any known data quality issues, NULL columns, missing periods, or fields that behave unexpectedly in this client's data.
A16: OPEN QUESTIONS (To Be Resolved with Client)
A17: Q1: Fiscal Calendar | B17: Confirm: Does the client's fiscal year align with the calendar year, or does it start in a different month? This affects all YTD, QTD and fiscal_year filters in every query. Aligned with calendar year
A18: Q2: Budget Version | B18: Which budget version should be used as the default baseline? Options: Original Annual Budget, Latest Revised Budget, Rolling Forecast. Confirm column name in the database if different from budget_net_revenue_reporting_amount. No budget
A19: Q3: Multi-Currency | B19: Should responses always show USD (reporting currency), or should some metrics show local currency? If local currency is needed, which tables and columns contain the local amounts? EUR only
A20: Q4: Data Refresh Frequency | B20: How often is the database refreshed? Daily, weekly, monthly? This affects how 'current' / 'real-time' questions should be answered. "Fake" data refresh should be enabled, ideally twice
A22: ROUNDING & SIGN CONVENTIONS (Summary)
